[
  {
    "slug": "2001-a-space-odyssey-by-arthur-c-clarke",
    "title": "2001: A Space Odyssey",
    "subtitle": null,
    "sortTitle": "2001: A Space Odyssey",
    "grade": "A+",
    "gradeValue": 13,
    "kind": "Novel",
    "authors": [
      {
        "slug": "arthur-c-clarke",
        "notes": null,
        "name": "Arthur C. Clarke",
        "sortName": "Clarke, Arthur C."
      }
    ],
    "readings": [
      {
        "date": "2024-01-15",
        "isAudiobook": false,
        "abandoned": false,
        "readingTime": 7,
        "readingSequence": 1
      }
    ],
    "includedInSlugs": [],
    "reviewDate": "2024-01-15",
    "reviewSequence": 1,
    "moreByAuthors": [],
    "moreReviews": [],
    "includedWorks": [],
    "workYearSequence": 1,
    "authorSequence": 1,
    "titleSequence": 1,
    "gradeSequence": 1,
    "reviewYear": "2024",
    "reviewed": true,
    "workYear": "2000"
  },
  {
    "slug": "about-face-by-david-h-hackworth-julie-sherman",
    "title": "About Face",
    "subtitle": "The Odyssey of an American Warrior",
    "sortTitle": "About Face: The Odyssey of an American Warrior",
    "grade": "A-",
    "gradeValue": 11,
    "kind": "Nonfiction",
    "authors": [
      {
        "slug": "david-h-hackworth",
        "notes": null,
        "name": "David H. Hackworth",
        "sortName": "Hackworth, David H."
      },
      {
        "slug": "julie-sherman",
        "notes": null,
        "name": "Julie Sherman",
        "sortName": "Sherman, Julie"
      }
    ],
    "readings": [
      {
        "date": "2022-09-05",
        "isAudiobook": true,
        "abandoned": false,
        "readingTime": 8,
        "readingSequence": 1
      }
    ],
    "includedInSlugs": [],
    "moreByAuthors": [],
    "moreReviews": [
      {
        "title": "The Woods Are Dark",
        "kind": "Novel",
        "slug": "the-woods-are-dark-by-richard-laymon",
        "grade": "C+",
        "includedInSlugs": [],
        "authors": [
          {
            "name": "Richard Laymon",
            "notes": null
          }
        ],
        "gradeValue": 7,
        "reviewDate": "2022-01-01",
        "reviewSequence": 3,
        "sortTitle": "Woods Are Dark",
        "subtitle": null,
        "workYear": "2000",
        "reviewYear": "2022"
      },
      {
        "title": "'Salem's Lot",
        "kind": "Novel",
        "slug": "salems-lot-by-stephen-king",
        "grade": "B",
        "includedInSlugs": [],
        "authors": [
          {
            "name": "Stephen King",
            "notes": null
          }
        ],
        "gradeValue": 9,
        "reviewDate": "2022-01-01",
        "reviewSequence": 4,
        "sortTitle": "'Salem's Lot",
        "subtitle": null,
        "workYear": "2000",
        "reviewYear": "2022"
      },
      {
        "title": "Altar",
        "kind": "Short Story",
        "slug": "altar-by-philip-fracassi",
        "grade": "A-",
        "includedInSlugs": [
          "behold-the-void-by-philip-fracassi"
        ],
        "authors": [
          {
            "name": "Philip Fracassi",
            "notes": null
          }
        ],
        "gradeValue": 11,
        "reviewDate": "2022-01-01",
        "reviewSequence": 6,
        "sortTitle": "Altar",
        "subtitle": null,
        "workYear": "2000",
        "reviewYear": "2022"
      },
      {
        "title": "Behold the Void",
        "kind": "Collection",
        "slug": "behold-the-void-by-philip-fracassi",
        "grade": "B+",
        "includedInSlugs": [],
        "authors": [
          {
            "name": "Philip Fracassi",
            "notes": null
          }
        ],
        "gradeValue": 10,
        "reviewDate": "2022-01-01",
        "reviewSequence": 8,
        "sortTitle": "Behold the Void",
        "subtitle": null,
        "workYear": "2000",
        "reviewYear": "2022"
      }
    ],
    "includedWorks": [],
    "reviewDate": "2022-09-05",
    "reviewSequence": 2,
    "workYearSequence": 2,
    "authorSequence": 2,
    "titleSequence": 2,
    "gradeSequence": 2,
    "reviewYear": "2022",
    "reviewed": true,
    "workYear": "2000"
  },
  {
    "slug": "altar-by-philip-fracassi",
    "title": "Altar",
    "subtitle": null,
    "sortTitle": "Altar",
    "grade": "A-",
    "gradeValue": 11,
    "kind": "Short Story",
    "authors": [
      {
        "slug": "philip-fracassi",
        "notes": null,
        "name": "Philip Fracassi",
        "sortName": "Fracassi, Philip"
      }
    ],
    "readings": [
      {
        "date": "2022-04-18",
        "isAudiobook": false,
        "abandoned": false,
        "readingTime": 1,
        "readingSequence": 1
      }
    ],
    "includedInSlugs": [
      "behold-the-void-by-philip-fracassi"
    ],
    "moreByAuthors": [
      {
        "name": "Philip Fracassi",
        "slug": "philip-fracassi",
        "sortName": "Fracassi, Philip",
        "reviewedWorks": [
          {
            "title": "Behold the Void",
            "kind": "Collection",
            "slug": "behold-the-void-by-philip-fracassi",
            "grade": "B+",
            "includedInSlugs": [],
            "authors": [
              {
                "name": "Philip Fracassi",
                "notes": null
              }
            ],
            "gradeValue": 10,
            "reviewDate": "2022-01-01",
            "reviewSequence": 20,
            "sortTitle": "Behold the Void",
            "subtitle": null,
            "workYear": "2017",
            "workYearSequence": 8,
            "authorSequence": 8,
            "titleSequence": 8,
            "gradeSequence": 8,
            "reviewYear": "2022"
          }
        ]
      }
    ],
    "moreReviews": [
      {
        "title": "'Salem's Lot",
        "kind": "Novel",
        "slug": "salems-lot-by-stephen-king",
        "grade": "B",
        "includedInSlugs": [],
        "authors": [
          {
            "name": "Stephen King",
            "notes": null
          }
        ],
        "gradeValue": 9,
        "reviewDate": "2022-01-01",
        "reviewSequence": 10,
        "sortTitle": "'Salem's Lot",
        "subtitle": null,
        "workYear": "2000",
        "reviewYear": "2022"
      },
      {
        "title": "About Face",
        "kind": "Nonfiction",
        "slug": "about-face-by-david-h-hackworth-julie-sherman",
        "grade": "A-",
        "includedInSlugs": [],
        "authors": [
          {
            "name": "David H. Hackworth",
            "notes": null
          },
          {
            "name": "Julie Sherman",
            "notes": null
          }
        ],
        "gradeValue": 11,
        "reviewDate": "2022-01-01",
        "reviewSequence": 12,
        "sortTitle": "About Face",
        "subtitle": null,
        "workYear": "2000",
        "reviewYear": "2022"
      }
    ],
    "includedWorks": [],
    "reviewDate": "2022-04-18",
    "reviewSequence": 9,
    "workYearSequence": 3,
    "authorSequence": 3,
    "titleSequence": 3,
    "gradeSequence": 3,
    "reviewYear": "2022",
    "reviewed": true,
    "workYear": "2000"
  },
  {
    "slug": "behold-the-void-by-philip-fracassi",
    "title": "Behold the Void",
    "subtitle": null,
    "sortTitle": "Behold the Void",
    "grade": "B+",
    "gradeValue": 10,
    "kind": "Collection",
    "authors": [
      {
        "slug": "philip-fracassi",
        "notes": null,
        "name": "Philip Fracassi",
        "sortName": "Fracassi, Philip"
      }
    ],
    "readings": [
      {
        "date": "2022-05-07",
        "isAudiobook": false,
        "abandoned": false,
        "readingTime": 21,
        "readingSequence": 1
      }
    ],
    "includedInSlugs": [],
    "moreByAuthors": [
      {
        "name": "Philip Fracassi",
        "slug": "philip-fracassi",
        "sortName": "Fracassi, Philip",
        "reviewedWorks": [
          {
            "title": "Altar",
            "kind": "Short Story",
            "slug": "altar-by-philip-fracassi",
            "grade": "A-",
            "includedInSlugs": [
              "behold-the-void-by-philip-fracassi"
            ],
            "authors": [
              {
                "name": "Philip Fracassi",
                "notes": null
              }
            ],
            "gradeValue": 11,
            "reviewDate": "2022-01-01",
            "reviewSequence": 30,
            "sortTitle": "Altar",
            "subtitle": null,
            "workYear": "2016",
            "workYearSequence": 12,
            "authorSequence": 12,
            "titleSequence": 12,
            "gradeSequence": 12,
            "reviewYear": "2022"
          }
        ]
      }
    ],
    "moreReviews": [
      {
        "title": "'Salem's Lot",
        "kind": "Novel",
        "slug": "salems-lot-by-stephen-king",
        "grade": "B",
        "includedInSlugs": [],
        "authors": [
          {
            "name": "Stephen King",
            "notes": null
          }
        ],
        "gradeValue": 9,
        "reviewDate": "2022-01-01",
        "reviewSequence": 23,
        "sortTitle": "'Salem's Lot",
        "subtitle": null,
        "workYear": "2000",
        "reviewYear": "2022"
      },
      {
        "title": "About Face",
        "kind": "Nonfiction",
        "slug": "about-face-by-david-h-hackworth-julie-sherman",
        "grade": "A-",
        "includedInSlugs": [],
        "authors": [
          {
            "name": "David H. Hackworth",
            "notes": null
          },
          {
            "name": "Julie Sherman",
            "notes": null
          }
        ],
        "gradeValue": 11,
        "reviewDate": "2022-01-01",
        "reviewSequence": 25,
        "sortTitle": "About Face",
        "subtitle": null,
        "workYear": "2000",
        "reviewYear": "2022"
      }
    ],
    "includedWorks": [
      {
        "slug": "altar-by-philip-fracassi",
        "title": "Altar",
        "grade": "A-",
        "kind": "Short Story",
        "yearPublished": "2016",
        "authors": [
          {
            "name": "Philip Fracassi",
            "slug": "philip-fracassi"
          }
        ],
        "workYear": "2016",
        "reviewed": true
      },
      {
        "slug": "the-baby-farmer-by-philip-fracassi",
        "title": "The Baby Farmer",
        "grade": "C+",
        "kind": "Short Story",
        "yearPublished": "2017",
        "authors": [
          {
            "name": "Philip Fracassi",
            "slug": "philip-fracassi"
          }
        ],
        "workYear": "2017",
        "reviewed": true
      },
      {
        "slug": "coffin-by-philip-fracassi",
        "title": "Coffin",
        "grade": "C+",
        "kind": "Short Story",
        "yearPublished": "2017",
        "authors": [
          {
            "name": "Philip Fracassi",
            "slug": "philip-fracassi"
          }
        ],
        "workYear": "2017",
        "reviewed": true
      },
      {
        "slug": "fail-safe-by-philip-fracassi",
        "title": "Fail-Safe",
        "grade": "C",
        "kind": "Short Story",
        "yearPublished": "2017",
        "authors": [
          {
            "name": "Philip Fracassi",
            "slug": "philip-fracassi"
          }
        ],
        "workYear": "2017",
        "reviewed": true
      },
      {
        "slug": "the-horse-thief-by-philip-fracassi",
        "title": "The Horse Thief",
        "grade": "B",
        "kind": "Short Story",
        "yearPublished": "2017",
        "authors": [
          {
            "name": "Philip Fracassi",
            "slug": "philip-fracassi"
          }
        ],
        "workYear": "2017",
        "reviewed": true
      },
      {
        "slug": "mandala-by-philip-fracassi",
        "title": "Mandala",
        "grade": "B+",
        "kind": "Novella",
        "yearPublished": "2017",
        "authors": [
          {
            "name": "Philip Fracassi",
            "slug": "philip-fracassi"
          }
        ],
        "workYear": "2017",
        "reviewed": true
      },
      {
        "slug": "mother-by-philip-fracassi",
        "title": "Mother",
        "grade": "B-",
        "kind": "Short Story",
        "yearPublished": "2015",
        "authors": [
          {
            "name": "Philip Fracassi",
            "slug": "philip-fracassi"
          }
        ],
        "workYear": "2015",
        "reviewed": true
      },
      {
        "slug": "soft-construction-of-a-sunset-by-philip-fracassi",
        "title": "Soft Construction of a Sunset",
        "grade": "B-",
        "kind": "Short Story",
        "yearPublished": "2017",
        "authors": [
          {
            "name": "Philip Fracassi",
            "slug": "philip-fracassi"
          }
        ],
        "workYear": "2017",
        "reviewed": true
      },
      {
        "slug": "surfer-girl-by-philip-fracassi",
        "title": "Surfer Girl",
        "grade": "C+",
        "kind": "Short Story",
        "yearPublished": "2017",
        "authors": [
          {
            "name": "Philip Fracassi",
            "slug": "philip-fracassi"
          }
        ],
        "workYear": "2017",
        "reviewed": true
      }
    ],
    "reviewDate": "2022-05-07",
    "reviewSequence": 22,
    "workYearSequence": 10,
    "authorSequence": 10,
    "titleSequence": 10,
    "gradeSequence": 10,
    "reviewYear": "2022",
    "reviewed": true,
    "workYear": "2000"
  },
  {
    "slug": "cant-hurt-me-by-david-goggins",
    "title": "Can't Hurt Me",
    "subtitle": "Master Your Mind and Defy the Odds",
    "sortTitle": "Can't Hurt Me: Master Your Mind and Defy the Odds",
    "grade": "B",
    "gradeValue": 9,
    "kind": "Nonfiction",
    "authors": [
      {
        "slug": "david-goggins",
        "notes": null,
        "name": "David Goggins",
        "sortName": "Goggins, David"
      }
    ],
    "readings": [
      {
        "date": "2022-10-13",
        "isAudiobook": true,
        "abandoned": false,
        "readingTime": 10,
        "readingSequence": 1
      }
    ],
    "includedInSlugs": [],
    "moreByAuthors": [],
    "moreReviews": [
      {
        "title": "Casino Royale",
        "kind": "Novel",
        "slug": "casino-royale-by-ian-fleming",
        "grade": "B-",
        "includedInSlugs": [],
        "authors": [
          {
            "name": "Ian Fleming",
            "notes": null
          }
        ],
        "gradeValue": 8,
        "reviewDate": "2022-01-01",
        "reviewSequence": 41,
        "sortTitle": "Casino Royale",
        "subtitle": null,
        "workYear": "2000",
        "reviewYear": "2022"
      }
    ],
    "includedWorks": [],
    "reviewDate": "2022-10-13",
    "reviewSequence": 35,
    "workYearSequence": 17,
    "authorSequence": 17,
    "titleSequence": 17,
    "gradeSequence": 17,
    "reviewYear": "2022",
    "reviewed": true,
    "workYear": "2000"
  },
  {
    "slug": "casino-royale-by-ian-fleming",
    "title": "Casino Royale",
    "subtitle": null,
    "sortTitle": "Casino Royale",
    "grade": "B-",
    "gradeValue": 8,
    "kind": "Novel",
    "authors": [
      {
        "slug": "ian-fleming",
        "notes": null,
        "name": "Ian Fleming",
        "sortName": "Fleming, Ian"
      }
    ],
    "readings": [
      {
        "date": "2022-06-14",
        "isAudiobook": false,
        "abandoned": false,
        "readingTime": 7,
        "readingSequence": 1
      }
    ],
    "includedInSlugs": [],
    "moreByAuthors": [],
    "moreReviews": [
      {
        "title": "Can't Hurt Me",
        "kind": "Nonfiction",
        "slug": "cant-hurt-me-by-david-goggins",
        "grade": "B",
        "includedInSlugs": [],
        "authors": [
          {
            "name": "David Goggins",
            "notes": null
          }
        ],
        "gradeValue": 9,
        "reviewDate": "2022-01-01",
        "reviewSequence": 43,
        "sortTitle": "Can't Hurt Me",
        "subtitle": null,
        "workYear": "2000",
        "reviewYear": "2022"
      },
      {
        "title": "The Cellar",
        "kind": "Novel",
        "slug": "the-cellar-by-richard-laymon",
        "grade": "C+",
        "includedInSlugs": [],
        "authors": [
          {
            "name": "Richard Laymon",
            "notes": null
          }
        ],
        "gradeValue": 7,
        "reviewDate": "2022-01-01",
        "reviewSequence": 46,
        "sortTitle": "Cellar",
        "subtitle": null,
        "workYear": "2000",
        "reviewYear": "2022"
      },
      {
        "title": "Churchill",
        "kind": "Nonfiction",
        "slug": "churchill-by-andrew-roberts",
        "grade": "A-",
        "includedInSlugs": [],
        "authors": [
          {
            "name": "Andrew Roberts",
            "notes": null
          }
        ],
        "gradeValue": 11,
        "reviewDate": "2022-01-01",
        "reviewSequence": 47,
        "sortTitle": "Churchill",
        "subtitle": null,
        "workYear": "2000",
        "reviewYear": "2022"
      }
    ],
    "includedWorks": [],
    "reviewDate": "2022-06-14",
    "reviewSequence": 42,
    "workYearSequence": 18,
    "authorSequence": 18,
    "titleSequence": 18,
    "gradeSequence": 18,
    "reviewYear": "2022",
    "reviewed": true,
    "workYear": "2000"
  },
  {
    "slug": "churchill-by-andrew-roberts",
    "title": "Churchill",
    "subtitle": "Walking with Destiny",
    "sortTitle": "Churchill: Walking with Destiny",
    "grade": "A-",
    "gradeValue": 11,
    "kind": "Nonfiction",
    "authors": [
      {
        "slug": "andrew-roberts",
        "notes": null,
        "name": "Andrew Roberts",
        "sortName": "Roberts, Andrew"
      }
    ],
    "readings": [
      {
        "date": "2022-06-14",
        "isAudiobook": true,
        "abandoned": false,
        "readingTime": 25,
        "readingSequence": 1
      }
    ],
    "includedInSlugs": [],
    "moreByAuthors": [],
    "moreReviews": [
      {
        "title": "Casino Royale",
        "kind": "Novel",
        "slug": "casino-royale-by-ian-fleming",
        "grade": "B-",
        "includedInSlugs": [],
        "authors": [
          {
            "name": "Ian Fleming",
            "notes": null
          }
        ],
        "gradeValue": 8,
        "reviewDate": "2022-01-01",
        "reviewSequence": 51,
        "sortTitle": "Casino Royale",
        "subtitle": null,
        "workYear": "2000",
        "reviewYear": "2022"
      },
      {
        "title": "The Cellar",
        "kind": "Novel",
        "slug": "the-cellar-by-richard-laymon",
        "grade": "C+",
        "includedInSlugs": [],
        "authors": [
          {
            "name": "Richard Laymon",
            "notes": null
          }
        ],
        "gradeValue": 7,
        "reviewDate": "2022-01-01",
        "reviewSequence": 52,
        "sortTitle": "Cellar",
        "subtitle": null,
        "workYear": "2000",
        "reviewYear": "2022"
      }
    ],
    "includedWorks": [],
    "reviewDate": "2022-06-14",
    "reviewSequence": 49,
    "workYearSequence": 19,
    "authorSequence": 19,
    "titleSequence": 19,
    "gradeSequence": 19,
    "reviewYear": "2022",
    "reviewed": true,
    "workYear": "2000"
  },
  {
    "slug": "dracula-by-bram-stoker",
    "title": "Dracula",
    "subtitle": null,
    "sortTitle": "Dracula",
    "grade": "C+",
    "gradeValue": 7,
    "kind": "Novel",
    "authors": [
      {
        "slug": "bram-stoker",
        "notes": null,
        "name": "Bram Stoker",
        "sortName": "Stoker, Bram"
      }
    ],
    "readings": [
      {
        "date": "2022-07-09",
        "isAudiobook": true,
        "abandoned": false,
        "readingTime": 8,
        "readingSequence": 1
      }
    ],
    "includedInSlugs": [],
    "moreByAuthors": [],
    "moreReviews": [
      {
        "title": "Extreme Ownership",
        "kind": "Nonfiction",
        "slug": "extreme-ownership-by-jocko-willink-leif-babin",
        "grade": "A",
        "includedInSlugs": [],
        "authors": [
          {
            "name": "Jocko Willink",
            "notes": null
          },
          {
            "name": "Leif Babin",
            "notes": null
          }
        ],
        "gradeValue": 12,
        "reviewDate": "2022-01-01",
        "reviewSequence": 61,
        "sortTitle": "Extreme Ownership",
        "subtitle": null,
        "workYear": "2000",
        "reviewYear": "2022"
      }
    ],
    "includedWorks": [],
    "reviewDate": "2022-07-09",
    "reviewSequence": 56,
    "workYearSequence": 20,
    "authorSequence": 20,
    "titleSequence": 20,
    "gradeSequence": 20,
    "reviewYear": "2022",
    "reviewed": true,
    "workYear": "2000"
  },
  {
    "slug": "extreme-ownership-by-jocko-willink-leif-babin",
    "title": "Extreme Ownership",
    "subtitle": "How U.S. Navy SEALs Lead and Win",
    "sortTitle": "Extreme Ownership: How U.S. Navy SEALs Lead and Win",
    "grade": "A",
    "gradeValue": 12,
    "kind": "Nonfiction",
    "authors": [
      {
        "slug": "jocko-willink",
        "notes": null,
        "name": "Jocko Willink",
        "sortName": "Willink, Jocko"
      },
      {
        "slug": "leif-babin",
        "notes": null,
        "name": "Leif Babin",
        "sortName": "Babin, Leif"
      }
    ],
    "readings": [
      {
        "date": "2022-06-26",
        "isAudiobook": true,
        "abandoned": false,
        "readingTime": 1,
        "readingSequence": 1
      }
    ],
    "includedInSlugs": [],
    "moreByAuthors": [],
    "moreReviews": [
      {
        "title": "Dracula",
        "kind": "Novel",
        "slug": "dracula-by-bram-stoker",
        "grade": "C+",
        "includedInSlugs": [],
        "authors": [
          {
            "name": "Bram Stoker",
            "notes": null
          }
        ],
        "gradeValue": 7,
        "reviewDate": "2022-01-01",
        "reviewSequence": 65,
        "sortTitle": "Dracula",
        "subtitle": null,
        "workYear": "2000",
        "reviewYear": "2022"
      },
      {
        "title": "Fight Club",
        "kind": "Novel",
        "slug": "fight-club-by-chuck-palahniuk",
        "grade": "A-",
        "includedInSlugs": [],
        "authors": [
          {
            "name": "Chuck Palahniuk",
            "notes": null
          }
        ],
        "gradeValue": 11,
        "reviewDate": "2022-01-01",
        "reviewSequence": 69,
        "sortTitle": "Fight Club",
        "subtitle": null,
        "workYear": "2000",
        "reviewYear": "2022"
      }
    ],
    "includedWorks": [],
    "reviewDate": "2022-06-26",
    "reviewSequence": 63,
    "workYearSequence": 21,
    "authorSequence": 21,
    "titleSequence": 21,
    "gradeSequence": 21,
    "reviewYear": "2022",
    "reviewed": true,
    "workYear": "2000"
  },
  {
    "slug": "fight-club-by-chuck-palahniuk",
    "title": "Fight Club",
    "subtitle": null,
    "sortTitle": "Fight Club",
    "grade": "A-",
    "gradeValue": 11,
    "kind": "Novel",
    "authors": [
      {
        "slug": "chuck-palahniuk",
        "notes": null,
        "name": "Chuck Palahniuk",
        "sortName": "Palahniuk, Chuck"
      }
    ],
    "readings": [
      {
        "date": "2022-07-16",
        "isAudiobook": true,
        "abandoned": false,
        "readingTime": 2,
        "readingSequence": 1
      }
    ],
    "includedInSlugs": [],
    "moreByAuthors": [],
    "moreReviews": [
      {
        "title": "Extreme Ownership",
        "kind": "Nonfiction",
        "slug": "extreme-ownership-by-jocko-willink-leif-babin",
        "grade": "A",
        "includedInSlugs": [],
        "authors": [
          {
            "name": "Jocko Willink",
            "notes": null
          },
          {
            "name": "Leif Babin",
            "notes": null
          }
        ],
        "gradeValue": 12,
        "reviewDate": "2022-01-01",
        "reviewSequence": 71,
        "sortTitle": "Extreme Ownership",
        "subtitle": null,
        "workYear": "2000",
        "reviewYear": "2022"
      },
      {
        "title": "Fright Night",
        "kind": "Novel",
        "slug": "fright-night-by-john-skipp-craig-spector",
        "grade": "F",
        "includedInSlugs": [],
        "authors": [
          {
            "name": "John Skipp",
            "notes": null
          },
          {
            "name": "Craig Spector",
            "notes": null
          }
        ],
        "gradeValue": 1,
        "reviewDate": "2022-01-01",
        "reviewSequence": 74,
        "sortTitle": "Fright Night",
        "subtitle": null,
        "workYear": "2000",
        "reviewYear": "2022"
      }
    ],
    "includedWorks": [],
    "reviewDate": "2022-07-16",
    "reviewSequence": 70,
    "workYearSequence": 22,
    "authorSequence": 22,
    "titleSequence": 22,
    "gradeSequence": 22,
    "reviewYear": "2022",
    "reviewed": true,
    "workYear": "2000"
  },
  {
    "slug": "fright-night-by-john-skipp-craig-spector",
    "title": "Fright Night",
    "subtitle": null,
    "sortTitle": "Fright Night",
    "grade": "F",
    "gradeValue": 1,
    "kind": "Novel",
    "authors": [
      {
        "slug": "john-skipp",
        "notes": null,
        "name": "John Skipp",
        "sortName": "Skipp, John"
      },
      {
        "slug": "craig-spector",
        "notes": null,
        "name": "Craig Spector",
        "sortName": "Spector, Craig"
      }
    ],
    "readings": [
      {
        "date": "2023-01-21",
        "isAudiobook": false,
        "abandoned": false,
        "readingTime": 7,
        "readingSequence": 1
      }
    ],
    "includedInSlugs": [],
    "moreByAuthors": [],
    "moreReviews": [
      {
        "title": "Fight Club",
        "kind": "Novel",
        "slug": "fight-club-by-chuck-palahniuk",
        "grade": "A-",
        "includedInSlugs": [],
        "authors": [
          {
            "name": "Chuck Palahniuk",
            "notes": null
          }
        ],
        "gradeValue": 11,
        "reviewDate": "2022-01-01",
        "reviewSequence": 80,
        "sortTitle": "Fight Club",
        "subtitle": null,
        "workYear": "2000",
        "reviewYear": "2022"
      }
    ],
    "includedWorks": [],
    "reviewDate": "2023-01-21",
    "reviewSequence": 77,
    "workYearSequence": 23,
    "authorSequence": 23,
    "titleSequence": 23,
    "gradeSequence": 23,
    "reviewYear": "2023",
    "reviewed": true,
    "workYear": "2000"
  },
  {
    "slug": "living-with-a-seal-by-jesse-itzler",
    "title": "Living with a SEAL",
    "subtitle": "31 Days Training with the Toughest Man on the Planet",
    "sortTitle": "Living with a SEAL: 31 Days Training with the Toughest Man on the Planet",
    "grade": "Abandoned",
    "gradeValue": 0,
    "kind": "Nonfiction",
    "authors": [
      {
        "slug": "jesse-itzler",
        "notes": null,
        "name": "Jesse Itzler",
        "sortName": "Itzler, Jesse"
      }
    ],
    "readings": [
      {
        "date": "2022-06-01",
        "isAudiobook": false,
        "abandoned": true,
        "readingTime": 9,
        "readingSequence": 1
      }
    ],
    "includedInSlugs": [],
    "moreByAuthors": [],
    "moreReviews": [
      {
        "title": "The Lonely One",
        "kind": "Short Story",
        "slug": "the-lonely-one-by-richard-laymon",
        "grade": "C+",
        "includedInSlugs": [],
        "authors": [
          {
            "name": "Richard Laymon",
            "notes": null
          }
        ],
        "gradeValue": 7,
        "reviewDate": "2022-01-01",
        "reviewSequence": 88,
        "sortTitle": "Lonely One",
        "subtitle": null,
        "workYear": "2000",
        "reviewYear": "2022"
      },
      {
        "title": "Mandala",
        "kind": "Novella",
        "slug": "mandala-by-philip-fracassi",
        "grade": "B+",
        "includedInSlugs": [
          "behold-the-void-by-philip-fracassi"
        ],
        "authors": [
          {
            "name": "Philip Fracassi",
            "notes": null
          }
        ],
        "gradeValue": 10,
        "reviewDate": "2022-01-01",
        "reviewSequence": 90,
        "sortTitle": "Mandala",
        "subtitle": null,
        "workYear": "2000",
        "reviewYear": "2022"
      }
    ],
    "includedWorks": [],
    "reviewDate": "2022-06-01",
    "reviewSequence": 84,
    "workYearSequence": 24,
    "authorSequence": 24,
    "titleSequence": 24,
    "gradeSequence": 24,
    "reviewYear": "2022",
    "reviewed": true,
    "workYear": "2000"
  },
  {
    "slug": "mandala-by-philip-fracassi",
    "title": "Mandala",
    "subtitle": null,
    "sortTitle": "Mandala",
    "grade": "B+",
    "gradeValue": 10,
    "kind": "Novella",
    "authors": [
      {
        "slug": "philip-fracassi",
        "notes": null,
        "name": "Philip Fracassi",
        "sortName": "Fracassi, Philip"
      }
    ],
    "readings": [
      {
        "date": "2022-05-07",
        "isAudiobook": false,
        "abandoned": false,
        "readingTime": 7,
        "readingSequence": 1
      }
    ],
    "includedInSlugs": [
      "behold-the-void-by-philip-fracassi"
    ],
    "moreByAuthors": [
      {
        "name": "Philip Fracassi",
        "slug": "philip-fracassi",
        "sortName": "Fracassi, Philip",
        "reviewedWorks": [
          {
            "title": "Soft Construction of a Sunset",
            "kind": "Short Story",
            "slug": "soft-construction-of-a-sunset-by-philip-fracassi",
            "grade": "B-",
            "includedInSlugs": [
              "behold-the-void-by-philip-fracassi"
            ],
            "authors": [
              {
                "name": "Philip Fracassi",
                "notes": null
              }
            ],
            "gradeValue": 8,
            "reviewDate": "2022-01-01",
            "reviewSequence": 102,
            "sortTitle": "Soft Construction of a Sunset",
            "subtitle": null,
            "workYear": "2017",
            "workYearSequence": 30,
            "authorSequence": 30,
            "titleSequence": 30,
            "gradeSequence": 30,
            "reviewYear": "2022"
          }
        ]
      }
    ],
    "moreReviews": [
      {
        "title": "Living with a SEAL",
        "kind": "Nonfiction",
        "slug": "living-with-a-seal-by-jesse-itzler",
        "grade": "Abandoned",
        "includedInSlugs": [],
        "authors": [
          {
            "name": "Jesse Itzler",
            "notes": null
          }
        ],
        "gradeValue": 0,
        "reviewDate": "2022-01-01",
        "reviewSequence": 92,
        "sortTitle": "Living with a SEAL",
        "subtitle": null,
        "workYear": "2000",
        "reviewYear": "2022"
      },
      {
        "title": "The Lonely One",
        "kind": "Short Story",
        "slug": "the-lonely-one-by-richard-laymon",
        "grade": "C+",
        "includedInSlugs": [],
        "authors": [
          {
            "name": "Richard Laymon",
            "notes": null
          }
        ],
        "gradeValue": 7,
        "reviewDate": "2022-01-01",
        "reviewSequence": 93,
        "sortTitle": "Lonely One",
        "subtitle": null,
        "workYear": "2000",
        "reviewYear": "2022"
      }
    ],
    "includedWorks": [],
    "reviewDate": "2022-05-07",
    "reviewSequence": 91,
    "workYearSequence": 25,
    "authorSequence": 25,
    "titleSequence": 25,
    "gradeSequence": 25,
    "reviewYear": "2022",
    "reviewed": true,
    "workYear": "2000"
  },
  {
    "slug": "night-shift-by-stephen-king",
    "title": "Night Shift",
    "subtitle": null,
    "sortTitle": "Night Shift",
    "grade": "B",
    "gradeValue": 9,
    "kind": "Collection",
    "authors": [
      {
        "slug": "stephen-king",
        "notes": null,
        "name": "Stephen King",
        "sortName": "King, Stephen"
      }
    ],
    "readings": [
      {
        "date": "2012-05-14",
        "isAudiobook": false,
        "abandoned": false,
        "readingTime": 2,
        "readingSequence": 1
      }
    ],
    "includedInSlugs": [],
    "moreByAuthors": [
      {
        "name": "Stephen King",
        "slug": "stephen-king",
        "sortName": "King, Stephen",
        "reviewedWorks": [
          {
            "title": "The Shining",
            "kind": "Novel",
            "slug": "the-shining-by-stephen-king",
            "grade": "B",
            "includedInSlugs": [],
            "authors": [
              {
                "name": "Stephen King",
                "notes": null
              }
            ],
            "gradeValue": 9,
            "reviewDate": "2022-01-01",
            "reviewSequence": 112,
            "sortTitle": "Shining",
            "subtitle": null,
            "workYear": "1977",
            "workYearSequence": 34,
            "authorSequence": 34,
            "titleSequence": 34,
            "gradeSequence": 34,
            "reviewYear": "2022"
          }
        ]
      }
    ],
    "moreReviews": [
      {
        "title": "Out Are the Lights",
        "kind": "Novel",
        "slug": "out-are-the-lights-by-richard-laymon",
        "grade": "C-",
        "includedInSlugs": [
          "out-are-the-lights-and-other-tales-by-richard-laymon"
        ],
        "authors": [
          {
            "name": "Richard Laymon",
            "notes": null
          }
        ],
        "gradeValue": 5,
        "reviewDate": "2022-01-01",
        "reviewSequence": 108,
        "sortTitle": "Out Are the Lights",
        "subtitle": null,
        "workYear": "2000",
        "reviewYear": "2022"
      }
    ],
    "includedWorks": [
      {
        "slug": "battleground-by-stephen-king",
        "title": "Battleground",
        "grade": null,
        "kind": "Short Story",
        "yearPublished": "1972",
        "authors": [
          {
            "name": "Stephen King",
            "slug": "stephen-king"
          }
        ],
        "workYear": "1972",
        "reviewed": true
      },
      {
        "slug": "the-boogeyman-by-stephen-king",
        "title": "The Boogeyman",
        "grade": null,
        "kind": "Short Story",
        "yearPublished": "1973",
        "authors": [
          {
            "name": "Stephen King",
            "slug": "stephen-king"
          }
        ],
        "workYear": "1973",
        "reviewed": true
      },
      {
        "slug": "children-of-the-corn-by-stephen-king",
        "title": "Children of the Corn",
        "grade": null,
        "kind": "Short Story",
        "yearPublished": "1977",
        "authors": [
          {
            "name": "Stephen King",
            "slug": "stephen-king"
          }
        ],
        "workYear": "1977",
        "reviewed": true
      },
      {
        "slug": "graveyard-shift-by-stephen-king",
        "title": "Graveyard Shift",
        "grade": null,
        "kind": "Short Story",
        "yearPublished": "1970",
        "authors": [
          {
            "name": "Stephen King",
            "slug": "stephen-king"
          }
        ],
        "workYear": "1970",
        "reviewed": true
      },
      {
        "slug": "gray-matter-by-stephen-king",
        "title": "Gray Matter",
        "grade": null,
        "kind": "Short Story",
        "yearPublished": "1973",
        "authors": [
          {
            "name": "Stephen King",
            "slug": "stephen-king"
          }
        ],
        "workYear": "1973",
        "reviewed": true
      },
      {
        "slug": "i-am-the-doorway-by-stephen-king",
        "title": "I Am the Doorway",
        "grade": null,
        "kind": "Short Story",
        "yearPublished": "1971",
        "authors": [
          {
            "name": "Stephen King",
            "slug": "stephen-king"
          }
        ],
        "workYear": "1971",
        "reviewed": true
      },
      {
        "slug": "i-know-what-you-need-by-stephen-king",
        "title": "I Know What You Need",
        "grade": null,
        "kind": "Short Story",
        "yearPublished": "1976",
        "authors": [
          {
            "name": "Stephen King",
            "slug": "stephen-king"
          }
        ],
        "workYear": "1976",
        "reviewed": true
      },
      {
        "slug": "jerusalems-lot-by-stephen-king",
        "title": "Jerusalem's Lot",
        "grade": null,
        "kind": "Short Story",
        "yearPublished": "1978",
        "authors": [
          {
            "name": "Stephen King",
            "slug": "stephen-king"
          }
        ],
        "workYear": "1978",
        "reviewed": true
      },
      {
        "slug": "the-last-rung-on-the-ladder-by-stephen-king",
        "title": "The Last Rung on the Ladder",
        "grade": null,
        "kind": "Short Story",
        "yearPublished": "1978",
        "authors": [
          {
            "name": "Stephen King",
            "slug": "stephen-king"
          }
        ],
        "workYear": "1978",
        "reviewed": true
      },
      {
        "slug": "the-lawnmower-man-by-stephen-king",
        "title": "The Lawnmower Man",
        "grade": null,
        "kind": "Short Story",
        "yearPublished": "1975",
        "authors": [
          {
            "name": "Stephen King",
            "slug": "stephen-king"
          }
        ],
        "workYear": "1975",
        "reviewed": true
      },
      {
        "slug": "the-ledge-by-stephen-king",
        "title": "The Ledge",
        "grade": null,
        "kind": "Short Story",
        "yearPublished": "1976",
        "authors": [
          {
            "name": "Stephen King",
            "slug": "stephen-king"
          }
        ],
        "workYear": "1976",
        "reviewed": true
      },
      {
        "slug": "the-man-who-loved-flowers-by-stephen-king",
        "title": "The Man Who Loved Flowers",
        "grade": null,
        "kind": "Short Story",
        "yearPublished": "1977",
        "authors": [
          {
            "name": "Stephen King",
            "slug": "stephen-king"
          }
        ],
        "workYear": "1977",
        "reviewed": true
      },
      {
        "slug": "the-mangler-by-stephen-king",
        "title": "The Mangler",
        "grade": null,
        "kind": "Short Story",
        "yearPublished": "1972",
        "authors": [
          {
            "name": "Stephen King",
            "slug": "stephen-king"
          }
        ],
        "workYear": "1972",
        "reviewed": true
      },
      {
        "slug": "night-surf-by-stephen-king",
        "title": "Night Surf",
        "grade": null,
        "kind": "Short Story",
        "yearPublished": "1969",
        "authors": [
          {
            "name": "Stephen King",
            "slug": "stephen-king"
          }
        ],
        "workYear": "1969",
        "reviewed": true
      },
      {
        "slug": "one-for-the-road-by-stephen-king",
        "title": "One for the Road",
        "grade": null,
        "kind": "Short Story",
        "yearPublished": "1977",
        "authors": [
          {
            "name": "Stephen King",
            "slug": "stephen-king"
          }
        ],
        "workYear": "1977",
        "reviewed": true
      },
      {
        "slug": "quitters-inc-by-stephen-king",
        "title": "Quitters, Inc.",
        "grade": null,
        "kind": "Short Story",
        "yearPublished": "1978",
        "authors": [
          {
            "name": "Stephen King",
            "slug": "stephen-king"
          }
        ],
        "workYear": "1978",
        "reviewed": true
      },
      {
        "slug": "sometimes-they-come-back-by-stephen-king",
        "title": "Sometimes They Come Back",
        "grade": null,
        "kind": "Short Story",
        "yearPublished": "1974",
        "authors": [
          {
            "name": "Stephen King",
            "slug": "stephen-king"
          }
        ],
        "workYear": "1974",
        "reviewed": true
      },
      {
        "slug": "strawberry-spring-by-stephen-king",
        "title": "Strawberry Spring",
        "grade": null,
        "kind": "Short Story",
        "yearPublished": "1968",
        "authors": [
          {
            "name": "Stephen King",
            "slug": "stephen-king"
          }
        ],
        "workYear": "1968",
        "reviewed": true
      },
      {
        "slug": "trucks-by-stephen-king",
        "title": "Trucks",
        "grade": null,
        "kind": "Short Story",
        "yearPublished": "1973",
        "authors": [
          {
            "name": "Stephen King",
            "slug": "stephen-king"
          }
        ],
        "workYear": "1973",
        "reviewed": true
      },
      {
        "slug": "the-woman-in-the-room-by-stephen-king",
        "title": "The Woman in the Room",
        "grade": null,
        "kind": "Short Story",
        "yearPublished": "1978",
        "authors": [
          {
            "name": "Stephen King",
            "slug": "stephen-king"
          }
        ],
        "workYear": "1978",
        "reviewed": true
      }
    ],
    "reviewDate": "2012-05-14",
    "reviewSequence": 104,
    "workYearSequence": 32,
    "authorSequence": 32,
    "titleSequence": 32,
    "gradeSequence": 32,
    "reviewYear": "2012",
    "reviewed": true,
    "workYear": "2000"
  },
  {
    "slug": "out-are-the-lights-by-richard-laymon",
    "title": "Out Are the Lights",
    "subtitle": null,
    "sortTitle": "Out Are the Lights",
    "grade": "C-",
    "gradeValue": 5,
    "kind": "Novel",
    "authors": [
      {
        "slug": "richard-laymon",
        "notes": null,
        "name": "Richard Laymon",
        "sortName": "Laymon, Richard"
      }
    ],
    "readings": [
      {
        "date": "2014-04-28",
        "isAudiobook": false,
        "abandoned": false,
        "readingTime": 5,
        "readingSequence": 1
      },
      {
        "date": "2022-10-11",
        "isAudiobook": false,
        "abandoned": false,
        "readingTime": 18,
        "readingSequence": 1
      }
    ],
    "includedInSlugs": [
      "out-are-the-lights-and-other-tales-by-richard-laymon"
    ],
    "moreByAuthors": [
      {
        "name": "Richard Laymon",
        "slug": "richard-laymon",
        "sortName": "Laymon, Richard",
        "reviewedWorks": [
          {
            "title": "Roadside Pickup",
            "kind": "Short Story",
            "slug": "roadside-pickup-by-richard-laymon",
            "grade": "C-",
            "includedInSlugs": [
              "short-stories-volume-one-by-richard-laymon"
            ],
            "authors": [
              {
                "name": "Richard Laymon",
                "notes": null
              }
            ],
            "gradeValue": 5,
            "reviewDate": "2022-01-01",
            "reviewSequence": 124,
            "sortTitle": "Roadside Pickup",
            "subtitle": null,
            "workYear": "1974",
            "workYearSequence": 40,
            "authorSequence": 40,
            "titleSequence": 40,
            "gradeSequence": 40,
            "reviewYear": "2022"
          },
          {
            "title": "The Cellar",
            "kind": "Novel",
            "slug": "the-cellar-by-richard-laymon",
            "grade": "C+",
            "includedInSlugs": [],
            "authors": [
              {
                "name": "Richard Laymon",
                "notes": null
              }
            ],
            "gradeValue": 7,
            "reviewDate": "2022-01-01",
            "reviewSequence": 125,
            "sortTitle": "Cellar",
            "subtitle": null,
            "workYear": "1980",
            "workYearSequence": 41,
            "authorSequence": 41,
            "titleSequence": 41,
            "gradeSequence": 41,
            "reviewYear": "2022"
          },
          {
            "title": "The Woods Are Dark",
            "kind": "Novel",
            "slug": "the-woods-are-dark-by-richard-laymon",
            "grade": "C+",
            "includedInSlugs": [],
            "authors": [
              {
                "name": "Richard Laymon",
                "notes": null
              }
            ],
            "gradeValue": 7,
            "reviewDate": "2022-01-01",
            "reviewSequence": 126,
            "sortTitle": "Woods Are Dark",
            "subtitle": null,
            "workYear": "1981",
            "workYearSequence": 42,
            "authorSequence": 42,
            "titleSequence": 42,
            "gradeSequence": 42,
            "reviewYear": "2022"
          },
          {
            "title": "The Intruder",
            "kind": "Short Story",
            "slug": "the-intruder-by-richard-laymon",
            "grade": "C",
            "includedInSlugs": [],
            "authors": [
              {
                "name": "Richard Laymon",
                "notes": null
              }
            ],
            "gradeValue": 6,
            "reviewDate": "2022-01-01",
            "reviewSequence": 127,
            "sortTitle": "Intruder",
            "subtitle": null,
            "workYear": "1984",
            "workYearSequence": 43,
            "authorSequence": 43,
            "titleSequence": 43,
            "gradeSequence": 43,
            "reviewYear": "2022"
          }
        ]
      }
    ],
    "moreReviews": [
      {
        "title": "Night Shift",
        "kind": "Collection",
        "slug": "night-shift-by-stephen-king",
        "grade": "B",
        "includedInSlugs": [],
        "authors": [
          {
            "name": "Stephen King",
            "notes": null
          }
        ],
        "gradeValue": 9,
        "reviewDate": "2022-01-01",
        "reviewSequence": 119,
        "sortTitle": "Night Shift",
        "subtitle": null,
        "workYear": "2000",
        "reviewYear": "2022"
      }
    ],
    "includedWorks": [],
    "reviewDate": "2022-10-11",
    "reviewSequence": 117,
    "workYearSequence": 39,
    "authorSequence": 39,
    "titleSequence": 39,
    "gradeSequence": 39,
    "reviewYear": "2022",
    "reviewed": true,
    "workYear": "2000"
  },
  {
    "slug": "refugee-by-piers-anthony",
    "title": "Refugee",
    "subtitle": null,
    "sortTitle": "Refugee",
    "grade": "Abandoned",
    "gradeValue": 0,
    "kind": "Novel",
    "authors": [
      {
        "slug": "piers-anthony",
        "notes": null,
        "name": "Piers Anthony",
        "sortName": "Anthony, Piers"
      }
    ],
    "readings": [
      {
        "date": "2016-01-29",
        "isAudiobook": false,
        "abandoned": true,
        "readingTime": 11,
        "readingSequence": 1
      }
    ],
    "includedInSlugs": [],
    "moreByAuthors": [],
    "moreReviews": [
      {
        "title": "The Rise of Theodore Roosevelt",
        "kind": "Nonfiction",
        "slug": "the-rise-of-theodore-roosevelt-by-edmund-morris",
        "grade": "A-",
        "includedInSlugs": [],
        "authors": [
          {
            "name": "Edmund Morris",
            "notes": null
          }
        ],
        "gradeValue": 11,
        "reviewDate": "2022-01-01",
        "reviewSequence": 134,
        "sortTitle": "Rise of Theodore Roosevelt",
        "subtitle": null,
        "workYear": "2000",
        "reviewYear": "2022"
      },
      {
        "title": "Roadside Pickup",
        "kind": "Short Story",
        "slug": "roadside-pickup-by-richard-laymon",
        "grade": "C-",
        "includedInSlugs": [
          "short-stories-volume-one-by-richard-laymon"
        ],
        "authors": [
          {
            "name": "Richard Laymon",
            "notes": null
          }
        ],
        "gradeValue": 5,
        "reviewDate": "2022-01-01",
        "reviewSequence": 135,
        "sortTitle": "Roadside Pickup",
        "subtitle": null,
        "workYear": "2000",
        "reviewYear": "2022"
      }
    ],
    "includedWorks": [],
    "reviewDate": "2016-01-29",
    "reviewSequence": 130,
    "workYearSequence": 46,
    "authorSequence": 46,
    "titleSequence": 46,
    "gradeSequence": 46,
    "reviewYear": "2016",
    "reviewed": true,
    "workYear": "2000"
  },
  {
    "slug": "roadside-pickup-by-richard-laymon",
    "title": "Roadside Pickup",
    "subtitle": null,
    "sortTitle": "Roadside Pickup",
    "grade": "C-",
    "gradeValue": 5,
    "kind": "Short Story",
    "authors": [
      {
        "slug": "richard-laymon",
        "notes": null,
        "name": "Richard Laymon",
        "sortName": "Laymon, Richard"
      }
    ],
    "readings": [
      {
        "date": "2023-01-21",
        "isAudiobook": false,
        "abandoned": false,
        "readingTime": 1,
        "readingSequence": 1
      }
    ],
    "includedInSlugs": [
      "short-stories-volume-one-by-richard-laymon"
    ],
    "moreByAuthors": [
      {
        "name": "Richard Laymon",
        "slug": "richard-laymon",
        "sortName": "Laymon, Richard",
        "reviewedWorks": [
          {
            "title": "The Lonely One",
            "kind": "Short Story",
            "slug": "the-lonely-one-by-richard-laymon",
            "grade": "C+",
            "includedInSlugs": [],
            "authors": [
              {
                "name": "Richard Laymon",
                "notes": null
              }
            ],
            "gradeValue": 7,
            "reviewDate": "2022-01-01",
            "reviewSequence": 144,
            "sortTitle": "Lonely One",
            "subtitle": null,
            "workYear": "1985",
            "workYearSequence": 48,
            "authorSequence": 48,
            "titleSequence": 48,
            "gradeSequence": 48,
            "reviewYear": "2022"
          },
          {
            "title": "Tread Softly",
            "kind": "Novel",
            "slug": "tread-softly-by-richard-laymon",
            "grade": "C",
            "includedInSlugs": [],
            "authors": [
              {
                "name": "Richard Laymon",
                "notes": "as Richard Kelly"
              }
            ],
            "gradeValue": 6,
            "reviewDate": "2022-01-01",
            "reviewSequence": 145,
            "sortTitle": "Tread Softly",
            "subtitle": null,
            "workYear": "1987",
            "workYearSequence": 49,
            "authorSequence": 49,
            "titleSequence": 49,
            "gradeSequence": 49,
            "reviewYear": "2022"
          },
          {
            "title": "The Cellar",
            "kind": "Novel",
            "slug": "the-cellar-by-richard-laymon",
            "grade": "C+",
            "includedInSlugs": [],
            "authors": [
              {
                "name": "Richard Laymon",
                "notes": null
              }
            ],
            "gradeValue": 7,
            "reviewDate": "2022-01-01",
            "reviewSequence": 147,
            "sortTitle": "Cellar",
            "subtitle": null,
            "workYear": "1980",
            "workYearSequence": 51,
            "authorSequence": 51,
            "titleSequence": 51,
            "gradeSequence": 51,
            "reviewYear": "2022"
          },
          {
            "title": "The Woods Are Dark",
            "kind": "Novel",
            "slug": "the-woods-are-dark-by-richard-laymon",
            "grade": "C+",
            "includedInSlugs": [],
            "authors": [
              {
                "name": "Richard Laymon",
                "notes": null
              }
            ],
            "gradeValue": 7,
            "reviewDate": "2022-01-01",
            "reviewSequence": 148,
            "sortTitle": "Woods Are Dark",
            "subtitle": null,
            "workYear": "1981",
            "workYearSequence": 52,
            "authorSequence": 52,
            "titleSequence": 52,
            "gradeSequence": 52,
            "reviewYear": "2022"
          },
          {
            "title": "Out Are the Lights",
            "kind": "Novel",
            "slug": "out-are-the-lights-by-richard-laymon",
            "grade": "C-",
            "includedInSlugs": [
              "out-are-the-lights-and-other-tales-by-richard-laymon"
            ],
            "authors": [
              {
                "name": "Richard Laymon",
                "notes": null
              }
            ],
            "gradeValue": 5,
            "reviewDate": "2022-01-01",
            "reviewSequence": 149,
            "sortTitle": "Out Are the Lights",
            "subtitle": null,
            "workYear": "1982",
            "workYearSequence": 53,
            "authorSequence": 53,
            "titleSequence": 53,
            "gradeSequence": 53,
            "reviewYear": "2022"
          }
        ]
      }
    ],
    "moreReviews": [
      {
        "title": "Refugee",
        "kind": "Novel",
        "slug": "refugee-by-piers-anthony",
        "grade": "Abandoned",
        "includedInSlugs": [],
        "authors": [
          {
            "name": "Piers Anthony",
            "notes": null
          }
        ],
        "gradeValue": 0,
        "reviewDate": "2022-01-01",
        "reviewSequence": 139,
        "sortTitle": "Refugee",
        "subtitle": null,
        "workYear": "2000",
        "reviewYear": "2022"
      },
      {
        "title": "The Rise of Theodore Roosevelt",
        "kind": "Nonfiction",
        "slug": "the-rise-of-theodore-roosevelt-by-edmund-morris",
        "grade": "A-",
        "includedInSlugs": [],
        "authors": [
          {
            "name": "Edmund Morris",
            "notes": null
          }
        ],
        "gradeValue": 11,
        "reviewDate": "2022-01-01",
        "reviewSequence": 140,
        "sortTitle": "Rise of Theodore Roosevelt",
        "subtitle": null,
        "workYear": "2000",
        "reviewYear": "2022"
      }
    ],
    "includedWorks": [],
    "reviewDate": "2023-01-21",
    "reviewSequence": 137,
    "workYearSequence": 47,
    "authorSequence": 47,
    "titleSequence": 47,
    "gradeSequence": 47,
    "reviewYear": "2023",
    "reviewed": true,
    "workYear": "2000"
  },
  {
    "slug": "salems-lot-by-stephen-king",
    "title": "'Salem's Lot",
    "subtitle": null,
    "sortTitle": "'Salem's Lot",
    "grade": "B",
    "gradeValue": 9,
    "kind": "Novel",
    "authors": [
      {
        "slug": "stephen-king",
        "notes": null,
        "name": "Stephen King",
        "sortName": "King, Stephen"
      }
    ],
    "readings": [
      {
        "date": "2022-10-14",
        "isAudiobook": true,
        "abandoned": false,
        "readingTime": 8,
        "readingSequence": 1
      }
    ],
    "includedInSlugs": [],
    "moreByAuthors": [
      {
        "name": "Stephen King",
        "slug": "stephen-king",
        "sortName": "King, Stephen",
        "reviewedWorks": [
          {
            "title": "The Shining",
            "kind": "Novel",
            "slug": "the-shining-by-stephen-king",
            "grade": "B",
            "includedInSlugs": [],
            "authors": [
              {
                "name": "Stephen King",
                "notes": null
              }
            ],
            "gradeValue": 9,
            "reviewDate": "2022-01-01",
            "reviewSequence": 161,
            "sortTitle": "Shining",
            "subtitle": null,
            "workYear": "1977",
            "workYearSequence": 59,
            "authorSequence": 59,
            "titleSequence": 59,
            "gradeSequence": 59,
            "reviewYear": "2022"
          }
        ]
      }
    ],
    "moreReviews": [
      {
        "title": "The Woods Are Dark",
        "kind": "Novel",
        "slug": "the-woods-are-dark-by-richard-laymon",
        "grade": "C+",
        "includedInSlugs": [],
        "authors": [
          {
            "name": "Richard Laymon",
            "notes": null
          }
        ],
        "gradeValue": 7,
        "reviewDate": "2022-01-01",
        "reviewSequence": 153,
        "sortTitle": "Woods Are Dark",
        "subtitle": null,
        "workYear": "2000",
        "reviewYear": "2022"
      },
      {
        "title": "About Face",
        "kind": "Nonfiction",
        "slug": "about-face-by-david-h-hackworth-julie-sherman",
        "grade": "A-",
        "includedInSlugs": [],
        "authors": [
          {
            "name": "David H. Hackworth",
            "notes": null
          },
          {
            "name": "Julie Sherman",
            "notes": null
          }
        ],
        "gradeValue": 11,
        "reviewDate": "2022-01-01",
        "reviewSequence": 155,
        "sortTitle": "About Face",
        "subtitle": null,
        "workYear": "2000",
        "reviewYear": "2022"
      },
      {
        "title": "Altar",
        "kind": "Short Story",
        "slug": "altar-by-philip-fracassi",
        "grade": "A-",
        "includedInSlugs": [
          "behold-the-void-by-philip-fracassi"
        ],
        "authors": [
          {
            "name": "Philip Fracassi",
            "notes": null
          }
        ],
        "gradeValue": 11,
        "reviewDate": "2022-01-01",
        "reviewSequence": 156,
        "sortTitle": "Altar",
        "subtitle": null,
        "workYear": "2000",
        "reviewYear": "2022"
      }
    ],
    "includedWorks": [],
    "reviewDate": "2022-10-14",
    "reviewSequence": 150,
    "workYearSequence": 54,
    "authorSequence": 54,
    "titleSequence": 54,
    "gradeSequence": 54,
    "reviewYear": "2022",
    "reviewed": true,
    "workYear": "2000"
  },
  {
    "slug": "soft-construction-of-a-sunset-by-philip-fracassi",
    "title": "Soft Construction of a Sunset",
    "subtitle": null,
    "sortTitle": "Soft Construction of a Sunset",
    "grade": "B-",
    "gradeValue": 8,
    "kind": "Short Story",
    "authors": [
      {
        "slug": "philip-fracassi",
        "notes": null,
        "name": "Philip Fracassi",
        "sortName": "Fracassi, Philip"
      }
    ],
    "readings": [
      {
        "date": "2022-04-17",
        "isAudiobook": false,
        "abandoned": false,
        "readingTime": 1,
        "readingSequence": 1
      }
    ],
    "includedInSlugs": [
      "behold-the-void-by-philip-fracassi"
    ],
    "moreByAuthors": [
      {
        "name": "Philip Fracassi",
        "slug": "philip-fracassi",
        "sortName": "Fracassi, Philip",
        "reviewedWorks": [
          {
            "title": "Mandala",
            "kind": "Novella",
            "slug": "mandala-by-philip-fracassi",
            "grade": "B+",
            "includedInSlugs": [
              "behold-the-void-by-philip-fracassi"
            ],
            "authors": [
              {
                "name": "Philip Fracassi",
                "notes": null
              }
            ],
            "gradeValue": 10,
            "reviewDate": "2022-01-01",
            "reviewSequence": 171,
            "sortTitle": "Mandala",
            "subtitle": null,
            "workYear": "2017",
            "workYearSequence": 63,
            "authorSequence": 63,
            "titleSequence": 63,
            "gradeSequence": 63,
            "reviewYear": "2022"
          }
        ]
      }
    ],
    "moreReviews": [
      {
        "title": "The Shining",
        "kind": "Novel",
        "slug": "the-shining-by-stephen-king",
        "grade": "B",
        "includedInSlugs": [],
        "authors": [
          {
            "name": "Stephen King",
            "notes": null
          }
        ],
        "gradeValue": 9,
        "reviewDate": "2022-01-01",
        "reviewSequence": 165,
        "sortTitle": "Shining",
        "subtitle": null,
        "workYear": "2000",
        "reviewYear": "2022"
      },
      {
        "title": "The Skeptics' Guide to the Universe",
        "kind": "Nonfiction",
        "slug": "the-skeptics-guide-to-the-universe-by-steven-novella",
        "grade": "B+",
        "includedInSlugs": [],
        "authors": [
          {
            "name": "Steven Novella",
            "notes": null
          }
        ],
        "gradeValue": 10,
        "reviewDate": "2022-01-01",
        "reviewSequence": 166,
        "sortTitle": "Skeptics' Guide to the Universe",
        "subtitle": null,
        "workYear": "2000",
        "reviewYear": "2022"
      }
    ],
    "includedWorks": [],
    "reviewDate": "2022-04-17",
    "reviewSequence": 163,
    "workYearSequence": 61,
    "authorSequence": 61,
    "titleSequence": 61,
    "gradeSequence": 61,
    "reviewYear": "2022",
    "reviewed": true,
    "workYear": "2000"
  },
  {
    "slug": "the-cellar-by-richard-laymon",
    "title": "The Cellar",
    "subtitle": null,
    "sortTitle": "Cellar, The",
    "grade": "C+",
    "gradeValue": 7,
    "kind": "Novel",
    "authors": [
      {
        "slug": "richard-laymon",
        "notes": null,
        "name": "Richard Laymon",
        "sortName": "Laymon, Richard"
      }
    ],
    "readings": [
      {
        "date": "2014-02-24",
        "isAudiobook": false,
        "abandoned": false,
        "readingTime": 5,
        "readingSequence": 1
      },
      {
        "date": "2022-03-16",
        "isAudiobook": false,
        "abandoned": false,
        "readingTime": 10,
        "readingSequence": 1
      }
    ],
    "includedInSlugs": [],
    "moreByAuthors": [
      {
        "name": "Richard Laymon",
        "slug": "richard-laymon",
        "sortName": "Laymon, Richard",
        "reviewedWorks": [
          {
            "title": "Tread Softly",
            "kind": "Novel",
            "slug": "tread-softly-by-richard-laymon",
            "grade": "C",
            "includedInSlugs": [],
            "authors": [
              {
                "name": "Richard Laymon",
                "notes": "as Richard Kelly"
              }
            ],
            "gradeValue": 6,
            "reviewDate": "2022-01-01",
            "reviewSequence": 183,
            "sortTitle": "Tread Softly",
            "subtitle": null,
            "workYear": "1987",
            "workYearSequence": 69,
            "authorSequence": 69,
            "titleSequence": 69,
            "gradeSequence": 69,
            "reviewYear": "2022"
          },
          {
            "title": "Roadside Pickup",
            "kind": "Short Story",
            "slug": "roadside-pickup-by-richard-laymon",
            "grade": "C-",
            "includedInSlugs": [
              "short-stories-volume-one-by-richard-laymon"
            ],
            "authors": [
              {
                "name": "Richard Laymon",
                "notes": null
              }
            ],
            "gradeValue": 5,
            "reviewDate": "2022-01-01",
            "reviewSequence": 185,
            "sortTitle": "Roadside Pickup",
            "subtitle": null,
            "workYear": "1974",
            "workYearSequence": 71,
            "authorSequence": 71,
            "titleSequence": 71,
            "gradeSequence": 71,
            "reviewYear": "2022"
          },
          {
            "title": "The Woods Are Dark",
            "kind": "Novel",
            "slug": "the-woods-are-dark-by-richard-laymon",
            "grade": "C+",
            "includedInSlugs": [],
            "authors": [
              {
                "name": "Richard Laymon",
                "notes": null
              }
            ],
            "gradeValue": 7,
            "reviewDate": "2022-01-01",
            "reviewSequence": 186,
            "sortTitle": "Woods Are Dark",
            "subtitle": null,
            "workYear": "1981",
            "workYearSequence": 72,
            "authorSequence": 72,
            "titleSequence": 72,
            "gradeSequence": 72,
            "reviewYear": "2022"
          },
          {
            "title": "Out Are the Lights",
            "kind": "Novel",
            "slug": "out-are-the-lights-by-richard-laymon",
            "grade": "C-",
            "includedInSlugs": [
              "out-are-the-lights-and-other-tales-by-richard-laymon"
            ],
            "authors": [
              {
                "name": "Richard Laymon",
                "notes": null
              }
            ],
            "gradeValue": 5,
            "reviewDate": "2022-01-01",
            "reviewSequence": 187,
            "sortTitle": "Out Are the Lights",
            "subtitle": null,
            "workYear": "1982",
            "workYearSequence": 73,
            "authorSequence": 73,
            "titleSequence": 73,
            "gradeSequence": 73,
            "reviewYear": "2022"
          },
          {
            "title": "The Intruder",
            "kind": "Short Story",
            "slug": "the-intruder-by-richard-laymon",
            "grade": "C",
            "includedInSlugs": [],
            "authors": [
              {
                "name": "Richard Laymon",
                "notes": null
              }
            ],
            "gradeValue": 6,
            "reviewDate": "2022-01-01",
            "reviewSequence": 188,
            "sortTitle": "Intruder",
            "subtitle": null,
            "workYear": "1984",
            "workYearSequence": 74,
            "authorSequence": 74,
            "titleSequence": 74,
            "gradeSequence": 74,
            "reviewYear": "2022"
          }
        ]
      }
    ],
    "moreReviews": [
      {
        "title": "Casino Royale",
        "kind": "Novel",
        "slug": "casino-royale-by-ian-fleming",
        "grade": "B-",
        "includedInSlugs": [],
        "authors": [
          {
            "name": "Ian Fleming",
            "notes": null
          }
        ],
        "gradeValue": 8,
        "reviewDate": "2022-01-01",
        "reviewSequence": 179,
        "sortTitle": "Casino Royale",
        "subtitle": null,
        "workYear": "2000",
        "reviewYear": "2022"
      },
      {
        "title": "Churchill",
        "kind": "Nonfiction",
        "slug": "churchill-by-andrew-roberts",
        "grade": "A-",
        "includedInSlugs": [],
        "authors": [
          {
            "name": "Andrew Roberts",
            "notes": null
          }
        ],
        "gradeValue": 11,
        "reviewDate": "2022-01-01",
        "reviewSequence": 180,
        "sortTitle": "Churchill",
        "subtitle": null,
        "workYear": "2000",
        "reviewYear": "2022"
      }
    ],
    "includedWorks": [],
    "reviewDate": "2022-03-16",
    "reviewSequence": 176,
    "workYearSequence": 68,
    "authorSequence": 68,
    "titleSequence": 68,
    "gradeSequence": 68,
    "reviewYear": "2022",
    "reviewed": true,
    "workYear": "2000"
  },
  {
    "slug": "the-intruder-by-richard-laymon",
    "title": "The Intruder",
    "subtitle": null,
    "sortTitle": "Intruder",
    "grade": "C",
    "gradeValue": 6,
    "kind": "Short Story",
    "authors": [
      {
        "slug": "richard-laymon",
        "notes": null,
        "name": "Richard Laymon",
        "sortName": "Laymon, Richard"
      }
    ],
    "readings": [
      {
        "date": "2014-07-23",
        "isAudiobook": false,
        "abandoned": false,
        "readingTime": 1,
        "readingSequence": 1
      }
    ],
    "includedInSlugs": [],
    "moreByAuthors": [
      {
        "name": "Richard Laymon",
        "slug": "richard-laymon",
        "sortName": "Laymon, Richard",
        "reviewedWorks": [
          {
            "title": "The Cellar",
            "kind": "Novel",
            "slug": "the-cellar-by-richard-laymon",
            "grade": "C+",
            "includedInSlugs": [],
            "authors": [
              {
                "name": "Richard Laymon",
                "notes": null
              }
            ],
            "gradeValue": 7,
            "reviewDate": "2022-01-01",
            "reviewSequence": 196,
            "sortTitle": "Cellar",
            "subtitle": null,
            "workYear": "1980",
            "workYearSequence": 76,
            "authorSequence": 76,
            "titleSequence": 76,
            "gradeSequence": 76,
            "reviewYear": "2022"
          },
          {
            "title": "The Woods Are Dark",
            "kind": "Novel",
            "slug": "the-woods-are-dark-by-richard-laymon",
            "grade": "C+",
            "includedInSlugs": [],
            "authors": [
              {
                "name": "Richard Laymon",
                "notes": null
              }
            ],
            "gradeValue": 7,
            "reviewDate": "2022-01-01",
            "reviewSequence": 197,
            "sortTitle": "Woods Are Dark",
            "subtitle": null,
            "workYear": "1981",
            "workYearSequence": 77,
            "authorSequence": 77,
            "titleSequence": 77,
            "gradeSequence": 77,
            "reviewYear": "2022"
          },
          {
            "title": "Out Are the Lights",
            "kind": "Novel",
            "slug": "out-are-the-lights-by-richard-laymon",
            "grade": "C-",
            "includedInSlugs": [
              "out-are-the-lights-and-other-tales-by-richard-laymon"
            ],
            "authors": [
              {
                "name": "Richard Laymon",
                "notes": null
              }
            ],
            "gradeValue": 5,
            "reviewDate": "2022-01-01",
            "reviewSequence": 198,
            "sortTitle": "Out Are the Lights",
            "subtitle": null,
            "workYear": "1982",
            "workYearSequence": 78,
            "authorSequence": 78,
            "titleSequence": 78,
            "gradeSequence": 78,
            "reviewYear": "2022"
          },
          {
            "title": "The Lonely One",
            "kind": "Short Story",
            "slug": "the-lonely-one-by-richard-laymon",
            "grade": "C+",
            "includedInSlugs": [],
            "authors": [
              {
                "name": "Richard Laymon",
                "notes": null
              }
            ],
            "gradeValue": 7,
            "reviewDate": "2022-01-01",
            "reviewSequence": 201,
            "sortTitle": "Lonely One",
            "subtitle": null,
            "workYear": "1985",
            "workYearSequence": 81,
            "authorSequence": 81,
            "titleSequence": 81,
            "gradeSequence": 81,
            "reviewYear": "2022"
          }
        ]
      }
    ],
    "moreReviews": [],
    "includedWorks": [],
    "reviewDate": "2014-07-23",
    "reviewSequence": 189,
    "workYearSequence": 75,
    "authorSequence": 75,
    "titleSequence": 75,
    "gradeSequence": 75,
    "reviewYear": "2014",
    "reviewed": true,
    "workYear": "2000"
  },
  {
    "slug": "the-lonely-one-by-richard-laymon",
    "title": "The Lonely One",
    "subtitle": null,
    "sortTitle": "Lonely One",
    "grade": "C+",
    "gradeValue": 7,
    "kind": "Short Story",
    "authors": [
      {
        "slug": "richard-laymon",
        "notes": null,
        "name": "Richard Laymon",
        "sortName": "Laymon, Richard"
      }
    ],
    "readings": [
      {
        "date": "2015-01-28",
        "isAudiobook": false,
        "abandoned": false,
        "readingTime": 1,
        "readingSequence": 1
      },
      {
        "date": "2025-02-15",
        "isAudiobook": false,
        "abandoned": false,
        "readingTime": 1,
        "readingSequence": 1
      },
      {
        "date": "2014-10-28",
        "isAudiobook": false,
        "abandoned": false,
        "readingTime": 1,
        "readingSequence": 1
      }
    ],
    "includedInSlugs": [],
    "moreByAuthors": [
      {
        "name": "Richard Laymon",
        "slug": "richard-laymon",
        "sortName": "Laymon, Richard",
        "reviewedWorks": [
          {
            "title": "The Intruder",
            "kind": "Short Story",
            "slug": "the-intruder-by-richard-laymon",
            "grade": "C",
            "includedInSlugs": [],
            "authors": [
              {
                "name": "Richard Laymon",
                "notes": null
              }
            ],
            "gradeValue": 6,
            "reviewDate": "2022-01-01",
            "reviewSequence": 209,
            "sortTitle": "Intruder",
            "subtitle": null,
            "workYear": "1984",
            "workYearSequence": 83,
            "authorSequence": 83,
            "titleSequence": 83,
            "gradeSequence": 83,
            "reviewYear": "2022"
          },
          {
            "title": "Tread Softly",
            "kind": "Novel",
            "slug": "tread-softly-by-richard-laymon",
            "grade": "C",
            "includedInSlugs": [],
            "authors": [
              {
                "name": "Richard Laymon",
                "notes": "as Richard Kelly"
              }
            ],
            "gradeValue": 6,
            "reviewDate": "2022-01-01",
            "reviewSequence": 212,
            "sortTitle": "Tread Softly",
            "subtitle": null,
            "workYear": "1987",
            "workYearSequence": 86,
            "authorSequence": 86,
            "titleSequence": 86,
            "gradeSequence": 86,
            "reviewYear": "2022"
          },
          {
            "title": "Roadside Pickup",
            "kind": "Short Story",
            "slug": "roadside-pickup-by-richard-laymon",
            "grade": "C-",
            "includedInSlugs": [
              "short-stories-volume-one-by-richard-laymon"
            ],
            "authors": [
              {
                "name": "Richard Laymon",
                "notes": null
              }
            ],
            "gradeValue": 5,
            "reviewDate": "2022-01-01",
            "reviewSequence": 214,
            "sortTitle": "Roadside Pickup",
            "subtitle": null,
            "workYear": "1974",
            "workYearSequence": 88,
            "authorSequence": 88,
            "titleSequence": 88,
            "gradeSequence": 88,
            "reviewYear": "2022"
          }
        ]
      }
    ],
    "moreReviews": [
      {
        "title": "Living with a SEAL",
        "kind": "Nonfiction",
        "slug": "living-with-a-seal-by-jesse-itzler",
        "grade": "Abandoned",
        "includedInSlugs": [],
        "authors": [
          {
            "name": "Jesse Itzler",
            "notes": null
          }
        ],
        "gradeValue": 0,
        "reviewDate": "2022-01-01",
        "reviewSequence": 205,
        "sortTitle": "Living with a SEAL",
        "subtitle": null,
        "workYear": "2000",
        "reviewYear": "2022"
      },
      {
        "title": "Mandala",
        "kind": "Novella",
        "slug": "mandala-by-philip-fracassi",
        "grade": "B+",
        "includedInSlugs": [
          "behold-the-void-by-philip-fracassi"
        ],
        "authors": [
          {
            "name": "Philip Fracassi",
            "notes": null
          }
        ],
        "gradeValue": 10,
        "reviewDate": "2022-01-01",
        "reviewSequence": 207,
        "sortTitle": "Mandala",
        "subtitle": null,
        "workYear": "2000",
        "reviewYear": "2022"
      }
    ],
    "includedWorks": [],
    "reviewDate": "2025-02-15",
    "reviewSequence": 202,
    "workYearSequence": 82,
    "authorSequence": 82,
    "titleSequence": 82,
    "gradeSequence": 82,
    "reviewYear": "2025",
    "reviewed": true,
    "workYear": "2000"
  },
  {
    "slug": "the-rise-of-theodore-roosevelt-by-edmund-morris",
    "title": "The Rise of Theodore Roosevelt",
    "subtitle": null,
    "sortTitle": "Rise of Theodore Roosevelt",
    "grade": "A-",
    "gradeValue": 11,
    "kind": "Nonfiction",
    "authors": [
      {
        "slug": "edmund-morris",
        "notes": null,
        "name": "Edmund Morris",
        "sortName": "Morris, Edmund"
      }
    ],
    "readings": [
      {
        "date": "2022-05-07",
        "isAudiobook": true,
        "abandoned": false,
        "readingTime": 50,
        "readingSequence": 1
      }
    ],
    "includedInSlugs": [],
    "moreByAuthors": [],
    "moreReviews": [
      {
        "title": "Refugee",
        "kind": "Novel",
        "slug": "refugee-by-piers-anthony",
        "grade": "Abandoned",
        "includedInSlugs": [],
        "authors": [
          {
            "name": "Piers Anthony",
            "notes": null
          }
        ],
        "gradeValue": 0,
        "reviewDate": "2022-01-01",
        "reviewSequence": 218,
        "sortTitle": "Refugee",
        "subtitle": null,
        "workYear": "2000",
        "reviewYear": "2022"
      },
      {
        "title": "Roadside Pickup",
        "kind": "Short Story",
        "slug": "roadside-pickup-by-richard-laymon",
        "grade": "C-",
        "includedInSlugs": [
          "short-stories-volume-one-by-richard-laymon"
        ],
        "authors": [
          {
            "name": "Richard Laymon",
            "notes": null
          }
        ],
        "gradeValue": 5,
        "reviewDate": "2022-01-01",
        "reviewSequence": 219,
        "sortTitle": "Roadside Pickup",
        "subtitle": null,
        "workYear": "2000",
        "reviewYear": "2022"
      }
    ],
    "includedWorks": [],
    "reviewDate": "2022-05-07",
    "reviewSequence": 215,
    "workYearSequence": 89,
    "authorSequence": 89,
    "titleSequence": 89,
    "gradeSequence": 89,
    "reviewYear": "2022",
    "reviewed": true,
    "workYear": "2000"
  },
  {
    "slug": "the-shining-by-stephen-king",
    "title": "The Shining",
    "subtitle": null,
    "sortTitle": "Shining",
    "grade": "B",
    "gradeValue": 9,
    "kind": "Novel",
    "authors": [
      {
        "slug": "stephen-king",
        "notes": null,
        "name": "Stephen King",
        "sortName": "King, Stephen"
      }
    ],
    "readings": [
      {
        "date": "2011-11-06",
        "isAudiobook": false,
        "abandoned": false,
        "readingTime": 3,
        "readingSequence": 1
      },
      {
        "date": "2022-10-29",
        "isAudiobook": true,
        "abandoned": false,
        "readingTime": 14,
        "readingSequence": 1
      }
    ],
    "includedInSlugs": [],
    "moreByAuthors": [
      {
        "name": "Stephen King",
        "slug": "stephen-king",
        "sortName": "King, Stephen",
        "reviewedWorks": [
          {
            "title": "'Salem's Lot",
            "kind": "Novel",
            "slug": "salems-lot-by-stephen-king",
            "grade": "B",
            "includedInSlugs": [],
            "authors": [
              {
                "name": "Stephen King",
                "notes": null
              }
            ],
            "gradeValue": 9,
            "reviewDate": "2022-01-01",
            "reviewSequence": 230,
            "sortTitle": "'Salem's Lot",
            "subtitle": null,
            "workYear": "1975",
            "workYearSequence": 92,
            "authorSequence": 92,
            "titleSequence": 92,
            "gradeSequence": 92,
            "reviewYear": "2022"
          },
          {
            "title": "Night Shift",
            "kind": "Collection",
            "slug": "night-shift-by-stephen-king",
            "grade": "B",
            "includedInSlugs": [],
            "authors": [
              {
                "name": "Stephen King",
                "notes": null
              }
            ],
            "gradeValue": 9,
            "reviewDate": "2022-01-01",
            "reviewSequence": 233,
            "sortTitle": "Night Shift",
            "subtitle": null,
            "workYear": "1978",
            "workYearSequence": 95,
            "authorSequence": 95,
            "titleSequence": 95,
            "gradeSequence": 95,
            "reviewYear": "2022"
          }
        ]
      }
    ],
    "moreReviews": [
      {
        "title": "The Skeptics' Guide to the Universe",
        "kind": "Nonfiction",
        "slug": "the-skeptics-guide-to-the-universe-by-steven-novella",
        "grade": "B+",
        "includedInSlugs": [],
        "authors": [
          {
            "name": "Steven Novella",
            "notes": null
          }
        ],
        "gradeValue": 10,
        "reviewDate": "2022-01-01",
        "reviewSequence": 226,
        "sortTitle": "Skeptics' Guide to the Universe",
        "subtitle": null,
        "workYear": "2000",
        "reviewYear": "2022"
      },
      {
        "title": "Soft Construction of a Sunset",
        "kind": "Short Story",
        "slug": "soft-construction-of-a-sunset-by-philip-fracassi",
        "grade": "B-",
        "includedInSlugs": [
          "behold-the-void-by-philip-fracassi"
        ],
        "authors": [
          {
            "name": "Philip Fracassi",
            "notes": null
          }
        ],
        "gradeValue": 8,
        "reviewDate": "2022-01-01",
        "reviewSequence": 227,
        "sortTitle": "Soft Construction of a Sunset",
        "subtitle": null,
        "workYear": "2000",
        "reviewYear": "2022"
      }
    ],
    "includedWorks": [],
    "reviewDate": "2022-10-29",
    "reviewSequence": 222,
    "workYearSequence": 90,
    "authorSequence": 90,
    "titleSequence": 90,
    "gradeSequence": 90,
    "reviewYear": "2022",
    "reviewed": true,
    "workYear": "2000"
  },
  {
    "slug": "the-skeptics-guide-to-the-universe-by-steven-novella",
    "title": "The Skeptics' Guide to the Universe",
    "subtitle": "How to Know What's Really Real in a World Increasingly Full of Fake",
    "sortTitle": "Skeptics' Guide to the Universe: How to Know What's Really Real in a World Increasingly Full of Fake",
    "grade": "B+",
    "gradeValue": 10,
    "kind": "Nonfiction",
    "authors": [
      {
        "slug": "steven-novella",
        "notes": null,
        "name": "Steven Novella",
        "sortName": "Novella, Steven"
      }
    ],
    "readings": [
      {
        "date": "2022-10-29",
        "isAudiobook": true,
        "abandoned": false,
        "readingTime": 8,
        "readingSequence": 1
      }
    ],
    "includedInSlugs": [],
    "moreByAuthors": [],
    "moreReviews": [
      {
        "title": "The Shining",
        "kind": "Novel",
        "slug": "the-shining-by-stephen-king",
        "grade": "B",
        "includedInSlugs": [],
        "authors": [
          {
            "name": "Stephen King",
            "notes": null
          }
        ],
        "gradeValue": 9,
        "reviewDate": "2022-01-01",
        "reviewSequence": 238,
        "sortTitle": "Shining",
        "subtitle": null,
        "workYear": "2000",
        "reviewYear": "2022"
      },
      {
        "title": "Soft Construction of a Sunset",
        "kind": "Short Story",
        "slug": "soft-construction-of-a-sunset-by-philip-fracassi",
        "grade": "B-",
        "includedInSlugs": [
          "behold-the-void-by-philip-fracassi"
        ],
        "authors": [
          {
            "name": "Philip Fracassi",
            "notes": null
          }
        ],
        "gradeValue": 8,
        "reviewDate": "2022-01-01",
        "reviewSequence": 239,
        "sortTitle": "Soft Construction of a Sunset",
        "subtitle": null,
        "workYear": "2000",
        "reviewYear": "2022"
      }
    ],
    "includedWorks": [],
    "reviewDate": "2022-10-29",
    "reviewSequence": 235,
    "workYearSequence": 97,
    "authorSequence": 97,
    "titleSequence": 97,
    "gradeSequence": 97,
    "reviewYear": "2022",
    "reviewed": true,
    "workYear": "2000"
  },
  {
    "slug": "the-woods-are-dark-by-richard-laymon",
    "title": "The Woods Are Dark",
    "subtitle": null,
    "sortTitle": "Woods Are Dark",
    "grade": "C+",
    "gradeValue": 7,
    "kind": "Novel",
    "authors": [
      {
        "slug": "richard-laymon",
        "notes": null,
        "name": "Richard Laymon",
        "sortName": "Laymon, Richard"
      }
    ],
    "readings": [
      {
        "date": "2014-03-18",
        "isAudiobook": false,
        "abandoned": false,
        "readingTime": 5,
        "readingSequence": 1
      },
      {
        "date": "2022-09-11",
        "isAudiobook": true,
        "abandoned": false,
        "readingTime": 2,
        "readingSequence": 1
      }
    ],
    "includedInSlugs": [],
    "moreByAuthors": [
      {
        "name": "Richard Laymon",
        "slug": "richard-laymon",
        "sortName": "Laymon, Richard",
        "reviewedWorks": [
          {
            "title": "Roadside Pickup",
            "kind": "Short Story",
            "slug": "roadside-pickup-by-richard-laymon",
            "grade": "C-",
            "includedInSlugs": [
              "short-stories-volume-one-by-richard-laymon"
            ],
            "authors": [
              {
                "name": "Richard Laymon",
                "notes": null
              }
            ],
            "gradeValue": 5,
            "reviewDate": "2022-01-01",
            "reviewSequence": 250,
            "sortTitle": "Roadside Pickup",
            "subtitle": null,
            "workYear": "1974",
            "workYearSequence": 100,
            "authorSequence": 100,
            "titleSequence": 100,
            "gradeSequence": 100,
            "reviewYear": "2022"
          },
          {
            "title": "The Cellar",
            "kind": "Novel",
            "slug": "the-cellar-by-richard-laymon",
            "grade": "C+",
            "includedInSlugs": [],
            "authors": [
              {
                "name": "Richard Laymon",
                "notes": null
              }
            ],
            "gradeValue": 7,
            "reviewDate": "2022-01-01",
            "reviewSequence": 251,
            "sortTitle": "Cellar",
            "subtitle": null,
            "workYear": "1980",
            "workYearSequence": 101,
            "authorSequence": 101,
            "titleSequence": 101,
            "gradeSequence": 101,
            "reviewYear": "2022"
          },
          {
            "title": "Out Are the Lights",
            "kind": "Novel",
            "slug": "out-are-the-lights-by-richard-laymon",
            "grade": "C-",
            "includedInSlugs": [
              "out-are-the-lights-and-other-tales-by-richard-laymon"
            ],
            "authors": [
              {
                "name": "Richard Laymon",
                "notes": null
              }
            ],
            "gradeValue": 5,
            "reviewDate": "2022-01-01",
            "reviewSequence": 252,
            "sortTitle": "Out Are the Lights",
            "subtitle": null,
            "workYear": "1982",
            "workYearSequence": 102,
            "authorSequence": 102,
            "titleSequence": 102,
            "gradeSequence": 102,
            "reviewYear": "2022"
          },
          {
            "title": "The Intruder",
            "kind": "Short Story",
            "slug": "the-intruder-by-richard-laymon",
            "grade": "C",
            "includedInSlugs": [],
            "authors": [
              {
                "name": "Richard Laymon",
                "notes": null
              }
            ],
            "gradeValue": 6,
            "reviewDate": "2022-01-01",
            "reviewSequence": 253,
            "sortTitle": "Intruder",
            "subtitle": null,
            "workYear": "1984",
            "workYearSequence": 103,
            "authorSequence": 103,
            "titleSequence": 103,
            "gradeSequence": 103,
            "reviewYear": "2022"
          }
        ]
      }
    ],
    "moreReviews": [
      {
        "title": "Tread Softly",
        "kind": "Novel",
        "slug": "tread-softly-by-richard-laymon",
        "grade": "C",
        "includedInSlugs": [],
        "authors": [
          {
            "name": "Richard Laymon",
            "notes": "as Richard Kelly"
          }
        ],
        "gradeValue": 6,
        "reviewDate": "2022-01-01",
        "reviewSequence": 243,
        "sortTitle": "Tread Softly",
        "subtitle": null,
        "workYear": "2000",
        "reviewYear": "2022"
      },
      {
        "title": "'Salem's Lot",
        "kind": "Novel",
        "slug": "salems-lot-by-stephen-king",
        "grade": "B",
        "includedInSlugs": [],
        "authors": [
          {
            "name": "Stephen King",
            "notes": null
          }
        ],
        "gradeValue": 9,
        "reviewDate": "2022-01-01",
        "reviewSequence": 246,
        "sortTitle": "'Salem's Lot",
        "subtitle": null,
        "workYear": "2000",
        "reviewYear": "2022"
      },
      {
        "title": "About Face",
        "kind": "Nonfiction",
        "slug": "about-face-by-david-h-hackworth-julie-sherman",
        "grade": "A-",
        "includedInSlugs": [],
        "authors": [
          {
            "name": "David H. Hackworth",
            "notes": null
          },
          {
            "name": "Julie Sherman",
            "notes": null
          }
        ],
        "gradeValue": 11,
        "reviewDate": "2022-01-01",
        "reviewSequence": 248,
        "sortTitle": "About Face",
        "subtitle": null,
        "workYear": "2000",
        "reviewYear": "2022"
      }
    ],
    "includedWorks": [],
    "reviewDate": "2022-09-11",
    "reviewSequence": 242,
    "workYearSequence": 98,
    "authorSequence": 98,
    "titleSequence": 98,
    "gradeSequence": 98,
    "reviewYear": "2022",
    "reviewed": true,
    "workYear": "2000"
  },
  {
    "slug": "tread-softly-by-richard-laymon",
    "title": "Tread Softly",
    "subtitle": null,
    "sortTitle": "Tread Softly",
    "grade": "C",
    "gradeValue": 6,
    "kind": "Novel",
    "authors": [
      {
        "slug": "richard-laymon",
        "notes": "as Richard Kelly",
        "name": "Richard Laymon",
        "sortName": "Laymon, Richard"
      }
    ],
    "readings": [
      {
        "date": "2014-09-21",
        "isAudiobook": false,
        "abandoned": false,
        "readingTime": 27,
        "readingSequence": 1
      }
    ],
    "includedInSlugs": [],
    "moreByAuthors": [
      {
        "name": "Richard Laymon",
        "slug": "richard-laymon",
        "sortName": "Laymon, Richard",
        "reviewedWorks": [
          {
            "title": "The Lonely One",
            "kind": "Short Story",
            "slug": "the-lonely-one-by-richard-laymon",
            "grade": "C+",
            "includedInSlugs": [],
            "authors": [
              {
                "name": "Richard Laymon",
                "notes": null
              }
            ],
            "gradeValue": 7,
            "reviewDate": "2022-01-01",
            "reviewSequence": 264,
            "sortTitle": "Lonely One",
            "subtitle": null,
            "workYear": "1985",
            "workYearSequence": 108,
            "authorSequence": 108,
            "titleSequence": 108,
            "gradeSequence": 108,
            "reviewYear": "2022"
          },
          {
            "title": "Roadside Pickup",
            "kind": "Short Story",
            "slug": "roadside-pickup-by-richard-laymon",
            "grade": "C-",
            "includedInSlugs": [
              "short-stories-volume-one-by-richard-laymon"
            ],
            "authors": [
              {
                "name": "Richard Laymon",
                "notes": null
              }
            ],
            "gradeValue": 5,
            "reviewDate": "2022-01-01",
            "reviewSequence": 266,
            "sortTitle": "Roadside Pickup",
            "subtitle": null,
            "workYear": "1974",
            "workYearSequence": 110,
            "authorSequence": 110,
            "titleSequence": 110,
            "gradeSequence": 110,
            "reviewYear": "2022"
          },
          {
            "title": "The Cellar",
            "kind": "Novel",
            "slug": "the-cellar-by-richard-laymon",
            "grade": "C+",
            "includedInSlugs": [],
            "authors": [
              {
                "name": "Richard Laymon",
                "notes": null
              }
            ],
            "gradeValue": 7,
            "reviewDate": "2022-01-01",
            "reviewSequence": 267,
            "sortTitle": "Cellar",
            "subtitle": null,
            "workYear": "1980",
            "workYearSequence": 111,
            "authorSequence": 111,
            "titleSequence": 111,
            "gradeSequence": 111,
            "reviewYear": "2022"
          }
        ]
      }
    ],
    "moreReviews": [
      {
        "title": "The Woods Are Dark",
        "kind": "Novel",
        "slug": "the-woods-are-dark-by-richard-laymon",
        "grade": "C+",
        "includedInSlugs": [],
        "authors": [
          {
            "name": "Richard Laymon",
            "notes": null
          }
        ],
        "gradeValue": 7,
        "reviewDate": "2022-01-01",
        "reviewSequence": 261,
        "sortTitle": "Woods Are Dark",
        "subtitle": null,
        "workYear": "2000",
        "reviewYear": "2022"
      }
    ],
    "includedWorks": [],
    "reviewDate": "2014-09-21",
    "reviewSequence": 255,
    "workYearSequence": 105,
    "authorSequence": 105,
    "titleSequence": 105,
    "gradeSequence": 105,
    "reviewYear": "2014",
    "reviewed": true,
    "workYear": "2000"
  }
]