[
  {
    "id": "2016-06-10-01-writing-movies-for-fun-and-profit-by-robert-ben-garant-thomas-lennon-1",
    "sequence": "2016-06-01-2016-06-10-01-writing-movies-for-fun-and-profit-by-robert-ben-garant-thomas-lennon",
    "reviewSlug": null,
    "edition": "Hardcover",
    "kind": "Nonfiction",
    "date": "2016-06-01",
    "progress": "12%",
    "workYear": "2011",
    "title": "Writing Movies for Fun and Profit",
    "authors": [
      {
        "name": "Robert Ben Garant",
        "notes": null
      },
      {
        "name": "Thomas Lennon",
        "notes": null
      }
    ]
  },
  {
    "id": "2016-06-10-01-writing-movies-for-fun-and-profit-by-robert-ben-garant-thomas-lennon-2",
    "sequence": "2016-06-03-2016-06-10-01-writing-movies-for-fun-and-profit-by-robert-ben-garant-thomas-lennon",
    "reviewSlug": null,
    "edition": "Hardcover",
    "kind": "Nonfiction",
    "date": "2016-06-03",
    "progress": "23%",
    "workYear": "2011",
    "title": "Writing Movies for Fun and Profit",
    "authors": [
      {
        "name": "Robert Ben Garant",
        "notes": null
      },
      {
        "name": "Thomas Lennon",
        "notes": null
      }
    ]
  },
  {
    "id": "2016-06-10-01-writing-movies-for-fun-and-profit-by-robert-ben-garant-thomas-lennon-3",
    "sequence": "2016-06-04-2016-06-10-01-writing-movies-for-fun-and-profit-by-robert-ben-garant-thomas-lennon",
    "reviewSlug": null,
    "edition": "Hardcover",
    "kind": "Nonfiction",
    "date": "2016-06-04",
    "progress": "47%",
    "workYear": "2011",
    "title": "Writing Movies for Fun and Profit",
    "authors": [
      {
        "name": "Robert Ben Garant",
        "notes": null
      },
      {
        "name": "Thomas Lennon",
        "notes": null
      }
    ]
  },
  {
    "id": "2016-06-10-01-writing-movies-for-fun-and-profit-by-robert-ben-garant-thomas-lennon-4",
    "sequence": "2016-06-05-2016-06-10-01-writing-movies-for-fun-and-profit-by-robert-ben-garant-thomas-lennon",
    "reviewSlug": null,
    "edition": "Hardcover",
    "kind": "Nonfiction",
    "date": "2016-06-05",
    "progress": "55%",
    "workYear": "2011",
    "title": "Writing Movies for Fun and Profit",
    "authors": [
      {
        "name": "Robert Ben Garant",
        "notes": null
      },
      {
        "name": "Thomas Lennon",
        "notes": null
      }
    ]
  },
  {
    "id": "2016-06-10-01-writing-movies-for-fun-and-profit-by-robert-ben-garant-thomas-lennon-5",
    "sequence": "2016-06-06-2016-06-10-01-writing-movies-for-fun-and-profit-by-robert-ben-garant-thomas-lennon",
    "reviewSlug": null,
    "edition": "Hardcover",
    "kind": "Nonfiction",
    "date": "2016-06-06",
    "progress": "60%",
    "workYear": "2011",
    "title": "Writing Movies for Fun and Profit",
    "authors": [
      {
        "name": "Robert Ben Garant",
        "notes": null
      },
      {
        "name": "Thomas Lennon",
        "notes": null
      }
    ]
  },
  {
    "id": "2016-06-10-01-writing-movies-for-fun-and-profit-by-robert-ben-garant-thomas-lennon-6",
    "sequence": "2016-06-07-2016-06-10-01-writing-movies-for-fun-and-profit-by-robert-ben-garant-thomas-lennon",
    "reviewSlug": null,
    "edition": "Hardcover",
    "kind": "Nonfiction",
    "date": "2016-06-07",
    "progress": "71%",
    "workYear": "2011",
    "title": "Writing Movies for Fun and Profit",
    "authors": [
      {
        "name": "Robert Ben Garant",
        "notes": null
      },
      {
        "name": "Thomas Lennon",
        "notes": null
      }
    ]
  },
  {
    "id": "2016-06-10-01-writing-movies-for-fun-and-profit-by-robert-ben-garant-thomas-lennon-7",
    "sequence": "2016-06-08-2016-06-10-01-writing-movies-for-fun-and-profit-by-robert-ben-garant-thomas-lennon",
    "reviewSlug": null,
    "edition": "Hardcover",
    "kind": "Nonfiction",
    "date": "2016-06-08",
    "progress": "77%",
    "workYear": "2011",
    "title": "Writing Movies for Fun and Profit",
    "authors": [
      {
        "name": "Robert Ben Garant",
        "notes": null
      },
      {
        "name": "Thomas Lennon",
        "notes": null
      }
    ]
  },
  {
    "id": "2016-06-10-01-writing-movies-for-fun-and-profit-by-robert-ben-garant-thomas-lennon-8",
    "sequence": "2016-06-09-2016-06-10-01-writing-movies-for-fun-and-profit-by-robert-ben-garant-thomas-lennon",
    "reviewSlug": null,
    "edition": "Hardcover",
    "kind": "Nonfiction",
    "date": "2016-06-09",
    "progress": "85%",
    "workYear": "2011",
    "title": "Writing Movies for Fun and Profit",
    "authors": [
      {
        "name": "Robert Ben Garant",
        "notes": null
      },
      {
        "name": "Thomas Lennon",
        "notes": null
      }
    ]
  },
  {
    "id": "2016-06-10-01-writing-movies-for-fun-and-profit-by-robert-ben-garant-thomas-lennon-9",
    "sequence": "2016-06-10-2016-06-10-01-writing-movies-for-fun-and-profit-by-robert-ben-garant-thomas-lennon",
    "reviewSlug": null,
    "edition": "Hardcover",
    "kind": "Nonfiction",
    "date": "2016-06-10",
    "progress": "Finished",
    "workYear": "2011",
    "title": "Writing Movies for Fun and Profit",
    "authors": [
      {
        "name": "Robert Ben Garant",
        "notes": null
      },
      {
        "name": "Thomas Lennon",
        "notes": null
      }
    ]
  }
]