{
  "name": "Nigel Andrews",
  "sortName": "Andrews, Nigel",
  "slug": "nigel-andrews",
  "reviewedWorks": [
    {
      "id": "true-myths-by-nigel-andrews",
      "reviewSequence": "2013-04-16-01-true-myths-by-nigel-andrews",
      "reviewSlug": "true-myths-by-nigel-andrews",
      "title": "True Myths",
      "sortTitle": "True Myths: The Life and Times of Arnold Schwarzenegger",
      "workYear": "1996",
      "grade": "D+",
      "kind": "Nonfiction",
      "reviewDate": "2013-04-16",
      "authors": [
        {
          "name": "Nigel Andrews",
          "sortName": "Andrews, Nigel",
          "slug": "nigel-andrews",
          "notes": null
        }
      ]
    }
  ]
}