{
  "name": "Robert Greene",
  "sortName": "Greene, Robert",
  "slug": "robert-greene",
  "reviewedWorks": [
    {
      "id": "the-48-laws-of-power-by-robert-greene",
      "reviewSequence": "2022-07-15-01",
      "reviewSlug": "the-48-laws-of-power-by-robert-greene",
      "title": "The 48 Laws of Power",
      "sortTitle": "48 Laws of Power",
      "workYear": "1998",
      "grade": "D+",
      "kind": "Nonfiction",
      "reviewDate": "2022-07-15",
      "authors": [
        {
          "name": "Robert Greene",
          "sortName": "Greene, Robert",
          "slug": "robert-greene",
          "notes": null
        }
      ]
    }
  ]
}