{
  "name": "Kathe Koja",
  "sortName": "Koja, Kathe",
  "slug": "kathe-koja",
  "reviewedWorks": [
    {
      "reviewSequence": 70,
      "title": "The Cipher",
      "reviewed": true,
      "subtitle": null,
      "workYear": "1991",
      "workYearSequence": 274,
      "authorSequence": 260,
      "titleSequence": 92,
      "kind": "Novel",
      "slug": "the-cipher-by-kathe-koja",
      "sortTitle": "Cipher",
      "grade": "B",
      "gradeValue": 9,
      "gradeSequence": 64,
      "reviewDate": "2023-01-29",
      "reviewYear": "2023",
      "authors": [
        {
          "slug": "kathe-koja",
          "notes": null,
          "name": "Kathe Koja",
          "sortName": "Koja, Kathe"
        }
      ],
      "includedInSlugs": []
    }
  ]
}