{
  "name": "Richard Laymon",
  "sortName": "Laymon, Richard",
  "slug": "richard-laymon",
  "reviewCount": 10,
  "reviewedWorks": [
    {
      "id": "beware-by-richard-laymon",
      "sequence": "2014-06-27-01-beware-by-richard-laymon",
      "slug": "beware-by-richard-laymon",
      "title": "Beware!",
      "sortTitle": "Beware!",
      "workYear": "1985",
      "grade": "C",
      "gradeValue": 6,
      "kind": "Novel",
      "reviewDate": "2014-06-27",
      "authors": [
        {
          "slug": "richard-laymon",
          "notes": null,
          "name": "Richard Laymon"
        }
      ],
      "reviewYear": "2014"
    },
    {
      "id": "the-cellar-by-richard-laymon",
      "sequence": "2022-03-16-01-the-cellar-by-richard-laymon",
      "slug": "the-cellar-by-richard-laymon",
      "title": "The Cellar",
      "sortTitle": "Cellar, The",
      "workYear": "1980",
      "grade": "C+",
      "gradeValue": 7,
      "kind": "Novel",
      "reviewDate": "2022-03-16",
      "authors": [
        {
          "slug": "richard-laymon",
          "notes": null,
          "name": "Richard Laymon"
        }
      ],
      "reviewYear": "2022"
    },
    {
      "id": "desert-pickup-by-richard-laymon",
      "sequence": "2022-04-03-01-desert-pickup-by-richard-laymon",
      "slug": "desert-pickup-by-richard-laymon",
      "title": "Desert Pickup",
      "sortTitle": "Desert Pickup",
      "workYear": "1970",
      "grade": "C-",
      "gradeValue": 5,
      "kind": "Short Story",
      "reviewDate": "2022-04-03",
      "authors": [
        {
          "slug": "richard-laymon",
          "notes": null,
          "name": "Richard Laymon"
        }
      ],
      "reviewYear": "2022"
    },
    {
      "id": "the-intruder-by-richard-laymon",
      "sequence": "2014-07-23-01-the-intruder-by-richard-laymon",
      "slug": "the-intruder-by-richard-laymon",
      "title": "The Intruder",
      "sortTitle": "Intruder",
      "workYear": "1984",
      "grade": "C",
      "gradeValue": 6,
      "kind": "Short Story",
      "reviewDate": "2014-07-23",
      "authors": [
        {
          "slug": "richard-laymon",
          "notes": null,
          "name": "Richard Laymon"
        }
      ],
      "reviewYear": "2014"
    },
    {
      "id": "the-last-hand-by-richard-laymon",
      "sequence": "2014-07-13-01-the-last-hand-by-richard-laymon",
      "slug": "the-last-hand-by-richard-laymon",
      "title": "The Last Hand",
      "sortTitle": "Last Hand",
      "workYear": "1985",
      "grade": "D",
      "gradeValue": 3,
      "kind": "Short Story",
      "reviewDate": "2014-07-13",
      "authors": [
        {
          "slug": "richard-laymon",
          "notes": null,
          "name": "Richard Laymon"
        }
      ],
      "reviewYear": "2014"
    },
    {
      "id": "the-lonely-one-by-richard-laymon",
      "sequence": "2025-02-15-01-the-lonely-one-by-richard-laymon",
      "slug": "the-lonely-one-by-richard-laymon",
      "title": "The Lonely One",
      "sortTitle": "Lonely One",
      "workYear": "1985",
      "grade": "C+",
      "gradeValue": 7,
      "kind": "Short Story",
      "reviewDate": "2025-02-15",
      "authors": [
        {
          "slug": "richard-laymon",
          "notes": null,
          "name": "Richard Laymon"
        }
      ],
      "reviewYear": "2025"
    },
    {
      "id": "out-are-the-lights-by-richard-laymon",
      "sequence": "2022-10-11-01-out-are-the-lights-by-richard-laymon",
      "slug": "out-are-the-lights-by-richard-laymon",
      "title": "Out Are the Lights",
      "sortTitle": "Out Are the Lights",
      "workYear": "1982",
      "grade": "C-",
      "gradeValue": 5,
      "kind": "Novel",
      "reviewDate": "2022-10-11",
      "authors": [
        {
          "slug": "richard-laymon",
          "notes": null,
          "name": "Richard Laymon"
        }
      ],
      "reviewYear": "2022"
    },
    {
      "id": "roadside-pickup-by-richard-laymon",
      "sequence": "2023-01-21-01-roadside-pickup-by-richard-laymon",
      "slug": "roadside-pickup-by-richard-laymon",
      "title": "Roadside Pickup",
      "sortTitle": "Roadside Pickup",
      "workYear": "1974",
      "grade": "C-",
      "gradeValue": 5,
      "kind": "Short Story",
      "reviewDate": "2023-01-21",
      "authors": [
        {
          "slug": "richard-laymon",
          "notes": null,
          "name": "Richard Laymon"
        }
      ],
      "reviewYear": "2023"
    },
    {
      "id": "tread-softly-by-richard-laymon",
      "sequence": "2014-09-21-01-tread-softly-by-richard-laymon",
      "slug": "tread-softly-by-richard-laymon",
      "title": "Tread Softly",
      "sortTitle": "Tread Softly",
      "workYear": "1987",
      "grade": "C",
      "gradeValue": 6,
      "kind": "Novel",
      "reviewDate": "2014-09-21",
      "authors": [
        {
          "slug": "richard-laymon",
          "notes": "as Richard Kelly",
          "name": "Richard Laymon"
        }
      ],
      "reviewYear": "2014"
    },
    {
      "id": "the-woods-are-dark-by-richard-laymon",
      "sequence": "2022-09-11-02-the-woods-are-dark-by-richard-laymon",
      "slug": "the-woods-are-dark-by-richard-laymon",
      "title": "The Woods Are Dark",
      "sortTitle": "Woods Are Dark",
      "workYear": "1981",
      "grade": "C+",
      "gradeValue": 7,
      "kind": "Novel",
      "reviewDate": "2022-09-11",
      "authors": [
        {
          "slug": "richard-laymon",
          "notes": null,
          "name": "Richard Laymon"
        }
      ],
      "reviewYear": "2022"
    }
  ]
}